{
  "standard": [
    {
      "inventory_id": "12076",
      "part_num": "2343",
      "color_id": "297",
      "quantity": "8",
      "is_spare": "f",
      "img_url": "https://cdn.rebrickable.com/media/parts/elements/4505990.jpg",
      "name": "Equipment Goblet / Glass",
      "part_cat_id": "27",
      "part_material": "Plastic",
      "colorName": "Pearl Gold"
    },
    {
      "inventory_id": "12076",
      "part_num": "2357",
      "color_id": "4",
      "quantity": "2",
      "is_spare": "f",
      "img_url": "https://cdn.rebrickable.com/media/parts/elements/235721.jpg",
      "name": "Brick 2 x 2 Corner",
      "part_cat_id": "11",
      "part_material": "Plastic",
      "colorName": "Red"
    },
    {
      "inventory_id": "12076",
      "part_num": "2412b",
      "color_id": "297",
      "quantity": "9",
      "is_spare": "f",
      "img_url": "https://cdn.rebrickable.com/media/parts/elements/4490599.jpg",
      "name": "Tile Special 1 x 2 Grille with Bottom Groove",
      "part_cat_id": "15",
      "part_material": "Plastic",
      "colorName": "Pearl Gold"
    },
    {
      "inventory_id": "12076",
      "part_num": "2420",
      "color_id": "0",
      "quantity": "2",
      "is_spare": "f",
      "img_url": "https://cdn.rebrickable.com/media/parts/elements/242026.jpg",
      "name": "Plate 2 x 2 Corner",
      "part_cat_id": "14",
      "part_material": "Plastic",
      "colorName": "Black"
    },
    {
      "inventory_id": "12076",
      "part_num": "2431",
      "color_id": "14",
      "quantity": "1",
      "is_spare": "f",
      "img_url": "https://cdn.rebrickable.com/media/parts/elements/243124.jpg",
      "name": "Tile 1 x 4 with Groove",
      "part_cat_id": "19",
      "part_material": "Plastic",
      "colorName": "Yellow"
    },
    {
      "inventory_id": "12076",
      "part_num": "2431",
      "color_id": "0",
      "quantity": "2",
      "is_spare": "f",
      "img_url": "https://cdn.rebrickable.com/media/parts/elements/243126.jpg",
      "name": "Tile 1 x 4 with Groove",
      "part_cat_id": "19",
      "part_material": "Plastic",
      "colorName": "Black"
    },
    {
      "inventory_id": "12076",
      "part_num": "2444",
      "color_id": "71",
      "quantity": "4",
      "is_spare": "f",
      "img_url": "https://cdn.rebrickable.com/media/parts/elements/4211359.jpg",
      "name": "Plate Special 2 x 2 with 1 Pin Hole [Split Underside Ribs]",
      "part_cat_id": "9",
      "part_material": "Plastic",
      "colorName": "Light Bluish Gray"
    },
    {
      "inventory_id": "12076",
      "part_num": "2458",
      "color_id": "71",
      "quantity": "4",
      "is_spare": "f",
      "img_url": "https://cdn.rebrickable.com/media/parts/elements/4211364.jpg",
      "name": "Brick Special 1 x 2 with Pin",
      "part_cat_id": "5",
      "part_material": "Plastic",
      "colorName": "Light Bluish Gray"
    },
    {
      "inventory_id": "12076",
      "part_num": "2540",
      "color_id": "71",
      "quantity": "2",
      "is_spare": "f",
      "img_url": "https://cdn.rebrickable.com/media/parts/elements/4211632.jpg",
      "name": "Plate Special 1 x 2 Side Handle [Free Ends]",
      "part_cat_id": "9",
      "part_material": "Plastic",
      "colorName": "Light Bluish Gray"
    },
    {
      "inventory_id": "12076",
      "part_num": "2569",
      "color_id": "0",
      "quantity": "1",
      "is_spare": "f",
      "img_url": "https://cdn.rebrickable.com/media/parts/elements/256926.jpg",
      "name": "Antenna Whip 8H",
      "part_cat_id": "32",
      "part_material": "Plastic",
      "colorName": "Black"
    },
    {
      "inventory_id": "12076",
      "part_num": "2654",
      "color_id": "4",
      "quantity": "4",
      "is_spare": "f",
      "img_url": "https://cdn.rebrickable.com/media/parts/elements/4163711.jpg",
      "name": "Plate Round 2 x 2 with Rounded Bottom [Boat Stud]",
      "part_cat_id": "21",
      "part_material": "Plastic",
      "colorName": "Red"
    },
    {
      "inventory_id": "12076",
      "part_num": "2780",
      "color_id": "0",
      "quantity": "8",
      "is_spare": "f",
      "img_url": "https://cdn.rebrickable.com/media/parts/elements/4121715.jpg",
      "name": "Technic Pin with Friction Ridges Lengthwise and Center Slots",
      "part_cat_id": "53",
      "part_material": "Plastic",
      "colorName": "Black"
    },
    {
      "inventory_id": "12076",
      "part_num": "298c02",
      "color_id": "71",
      "quantity": "2",
      "is_spare": "f",
      "img_url": "https://cdn.rebrickable.com/media/parts/elements/4221775.jpg",
      "name": "Lever Small Base with Black Lever",
      "part_cat_id": "32",
      "part_material": "Plastic",
      "colorName": "Light Bluish Gray"
    },
    {
      "inventory_id": "12076",
      "part_num": "3001",
      "color_id": "4",
      "quantity": "2",
      "is_spare": "f",
      "img_url": "https://cdn.rebrickable.com/media/parts/elements/300121.jpg",
      "name": "Brick 2 x 4",
      "part_cat_id": "11",
      "part_material": "Plastic",
      "colorName": "Red"
    },
    {
      "inventory_id": "12076",
      "part_num": "30031",
      "color_id": "72",
      "quantity": "1",
      "is_spare": "f",
      "img_url": "https://cdn.rebrickable.com/media/parts/elements/4261908.jpg",
      "name": "Handlebars",
      "part_cat_id": "36",
      "part_material": "Plastic",
      "colorName": "Dark Bluish Gray"
    },
    {
      "inventory_id": "12076",
      "part_num": "3004",
      "color_id": "72",
      "quantity": "2",
      "is_spare": "f",
      "img_url": "https://cdn.rebrickable.com/media/parts/elements/4211088.jpg",
      "name": "Brick 1 x 2",
      "part_cat_id": "11",
      "part_material": "Plastic",
      "colorName": "Dark Bluish Gray"
    },
    {
      "inventory_id": "12076",
      "part_num": "3008",
      "color_id": "0",
      "quantity": "4",
      "is_spare": "f",
      "img_url": "https://cdn.rebrickable.com/media/parts/elements/300826.jpg",
      "name": "Brick 1 x 8",
      "part_cat_id": "11",
      "part_material": "Plastic",
      "colorName": "Black"
    },
    {
      "inventory_id": "12076",
      "part_num": "3010",
      "color_id": "71",
      "quantity": "1",
      "is_spare": "f",
      "img_url": "https://cdn.rebrickable.com/media/parts/elements/4211394.jpg",
      "name": "Brick 1 x 4",
      "part_cat_id": "11",
      "part_material": "Plastic",
      "colorName": "Light Bluish Gray"
    },
    {
      "inventory_id": "12076",
      "part_num": "30162",
      "color_id": "72",
      "quantity": "4",
      "is_spare": "f",
      "img_url": "https://cdn.rebrickable.com/media/parts/elements/4211051.jpg",
      "name": "Equipment Binoculars",
      "part_cat_id": "27",
      "part_material": "Plastic",
      "colorName": "Dark Bluish Gray"
    },
    {
      "inventory_id": "12076",
      "part_num": "3020",
      "color_id": "15",
      "quantity": "1",
      "is_spare": "f",
      "img_url": "https://cdn.rebrickable.com/media/parts/elements/302001.jpg",
      "name": "Plate 2 x 4",
      "part_cat_id": "14",
      "part_material": "Plastic",
      "colorName": "White"
    },
    {
      "inventory_id": "12076",
      "part_num": "3020",
      "color_id": "0",
      "quantity": "10",
      "is_spare": "f",
      "img_url": "https://cdn.rebrickable.com/media/parts/elements/302026.jpg",
      "name": "Plate 2 x 4",
      "part_cat_id": "14",
      "part_material": "Plastic",
      "colorName": "Black"
    },
    {
      "inventory_id": "12076",
      "part_num": "3020",
      "color_id": "14",
      "quantity": "1",
      "is_spare": "f",
      "img_url": "https://cdn.rebrickable.com/media/parts/elements/302024.jpg",
      "name": "Plate 2 x 4",
      "part_cat_id": "14",
      "part_material": "Plastic",
      "colorName": "Yellow"
    },
    {
      "inventory_id": "12076",
      "part_num": "3020",
      "color_id": "71",
      "quantity": "1",
      "is_spare": "f",
      "img_url": "https://cdn.rebrickable.com/media/parts/elements/4211395.jpg",
      "name": "Plate 2 x 4",
      "part_cat_id": "14",
      "part_material": "Plastic",
      "colorName": "Light Bluish Gray"
    },
    {
      "inventory_id": "12076",
      "part_num": "3021",
      "color_id": "85",
      "quantity": "3",
      "is_spare": "f",
      "img_url": "https://cdn.rebrickable.com/media/parts/elements/4225142.jpg",
      "name": "Plate 2 x 3",
      "part_cat_id": "14",
      "part_material": "Plastic",
      "colorName": "Dark Purple"
    },
    {
      "inventory_id": "12076",
      "part_num": "3022",
      "color_id": "15",
      "quantity": "1",
      "is_spare": "f",
      "img_url": "https://cdn.rebrickable.com/media/parts/elements/302201.jpg",
      "name": "Plate 2 x 2",
      "part_cat_id": "14",
      "part_material": "Plastic",
      "colorName": "White"
    },
    {
      "inventory_id": "12076",
      "part_num": "3022",
      "color_id": "0",
      "quantity": "3",
      "is_spare": "f",
      "img_url": "https://cdn.rebrickable.com/media/parts/elements/302226.jpg",
      "name": "Plate 2 x 2",
      "part_cat_id": "14",
      "part_material": "Plastic",
      "colorName": "Black"
    },
    {
      "inventory_id": "12076",
      "part_num": "3022",
      "color_id": "71",
      "quantity": "2",
      "is_spare": "f",
      "img_url": "https://cdn.rebrickable.com/media/parts/elements/4211397.jpg",
      "name": "Plate 2 x 2",
      "part_cat_id": "14",
      "part_material": "Plastic",
      "colorName": "Light Bluish Gray"
    },
    {
      "inventory_id": "12076",
      "part_num": "3023",
      "color_id": "71",
      "quantity": "1",
      "is_spare": "f",
      "img_url": "https://cdn.rebrickable.com/media/parts/elements/4211398.jpg",
      "name": "Plate 1 x 2",
      "part_cat_id": "14",
      "part_material": "Plastic",
      "colorName": "Light Bluish Gray"
    },
    {
      "inventory_id": "12076",
      "part_num": "3023",
      "color_id": "15",
      "quantity": "6",
      "is_spare": "f",
      "img_url": "https://cdn.rebrickable.com/media/parts/elements/302301.jpg",
      "name": "Plate 1 x 2",
      "part_cat_id": "14",
      "part_material": "Plastic",
      "colorName": "White"
    },
    {
      "inventory_id": "12076",
      "part_num": "3023",
      "color_id": "0",
      "quantity": "8",
      "is_spare": "f",
      "img_url": "https://cdn.rebrickable.com/media/parts/elements/302326.jpg",
      "name": "Plate 1 x 2",
      "part_cat_id": "14",
      "part_material": "Plastic",
      "colorName": "Black"
    },
    {
      "inventory_id": "12076",
      "part_num": "3033",
      "color_id": "0",
      "quantity": "2",
      "is_spare": "f",
      "img_url": "https://cdn.rebrickable.com/media/parts/elements/303326.jpg",
      "name": "Plate 6 x 10",
      "part_cat_id": "14",
      "part_material": "Plastic",
      "colorName": "Black"
    },
    {
      "inventory_id": "12076",
      "part_num": "3036",
      "color_id": "0",
      "quantity": "1",
      "is_spare": "f",
      "img_url": "https://cdn.rebrickable.com/media/parts/elements/303626.jpg",
      "name": "Plate 6 x 8",
      "part_cat_id": "14",
      "part_material": "Plastic",
      "colorName": "Black"
    },
    {
      "inventory_id": "12076",
      "part_num": "30360",
      "color_id": "0",
      "quantity": "2",
      "is_spare": "f",
      "img_url": "https://cdn.rebrickable.com/media/parts/elements/4141255.jpg",
      "name": "Cylinder 3 x 6 x 2 2/3 Horizontal Hollow Studs",
      "part_cat_id": "20",
      "part_material": "Plastic",
      "colorName": "Black"
    },
    {
      "inventory_id": "12076",
      "part_num": "30382",
      "color_id": "0",
      "quantity": "2",
      "is_spare": "f",
      "img_url": "https://cdn.rebrickable.com/media/parts/elements/4584332.jpg",
      "name": "Wedge Sloped 2 x 16 Triple",
      "part_cat_id": "6",
      "part_material": "Plastic",
      "colorName": "Black"
    },
    {
      "inventory_id": "12076",
      "part_num": "3040b",
      "color_id": "4",
      "quantity": "4",
      "is_spare": "f",
      "img_url": "https://cdn.rebrickable.com/media/parts/elements/4121934.jpg",
      "name": "Slope 45 2 x 1 with Bottom Pin",
      "part_cat_id": "3",
      "part_material": "Plastic",
      "colorName": "Red"
    },
    {
      "inventory_id": "12076",
      "part_num": "3040b",
      "color_id": "0",
      "quantity": "6",
      "is_spare": "f",
      "img_url": "https://cdn.rebrickable.com/media/parts/elements/304026.jpg",
      "name": "Slope 45 2 x 1 with Bottom Pin",
      "part_cat_id": "3",
      "part_material": "Plastic",
      "colorName": "Black"
    },
    {
      "inventory_id": "12076",
      "part_num": "30414",
      "color_id": "4",
      "quantity": "4",
      "is_spare": "f",
      "img_url": "https://cdn.rebrickable.com/media/parts/elements/4157223.jpg",
      "name": "Brick Special 1 x 4 with 4 Studs on One Side",
      "part_cat_id": "5",
      "part_material": "Plastic",
      "colorName": "Red"
    },
    {
      "inventory_id": "12076",
      "part_num": "3048c",
      "color_id": "4",
      "quantity": "1",
      "is_spare": "f",
      "img_url": "https://cdn.rebrickable.com/media/parts/elements/4195004.jpg",
      "name": "Slope 45 2 x 1 Triple with Ovoid Bottom Pin",
      "part_cat_id": "3",
      "part_material": "Plastic",
      "colorName": "Red"
    },
    {
      "inventory_id": "12076",
      "part_num": "3048c",
      "color_id": "0",
      "quantity": "2",
      "is_spare": "f",
      "img_url": "https://cdn.rebrickable.com/media/parts/elements/304826.jpg",
      "name": "Slope 45 2 x 1 Triple with Ovoid Bottom Pin",
      "part_cat_id": "3",
      "part_material": "Plastic",
      "colorName": "Black"
    },
    {
      "inventory_id": "12076",
      "part_num": "3068b",
      "color_id": "0",
      "quantity": "2",
      "is_spare": "f",
      "img_url": "https://cdn.rebrickable.com/media/parts/elements/306826.jpg",
      "name": "Tile 2 x 2 with Groove",
      "part_cat_id": "19",
      "part_material": "Plastic",
      "colorName": "Black"
    },
    {
      "inventory_id": "12076",
      "part_num": "32002",
      "color_id": "72",
      "quantity": "4",
      "is_spare": "f",
      "img_url": "https://cdn.rebrickable.com/media/parts/elements/4211050.jpg",
      "name": "Technic Pin 3/4",
      "part_cat_id": "53",
      "part_material": "Plastic",
      "colorName": "Dark Bluish Gray"
    },
    {
      "inventory_id": "12076",
      "part_num": "32018",
      "color_id": "71",
      "quantity": "2",
      "is_spare": "f",
      "img_url": "https://cdn.rebrickable.com/media/parts/elements/4211705.jpg",
      "name": "Technic Brick 1 x 14 [13 Holes]",
      "part_cat_id": "8",
      "part_material": "Plastic",
      "colorName": "Light Bluish Gray"
    },
    {
      "inventory_id": "12076",
      "part_num": "32064b",
      "color_id": "14",
      "quantity": "2",
      "is_spare": "f",
      "img_url": "https://cdn.rebrickable.com/media/parts/ldraw/14/32064d.png",
      "name": "Technic Brick 1 x 2 with Axle Hole Type 2 [X Opening]",
      "part_cat_id": "8",
      "part_material": "Plastic",
      "colorName": "Yellow"
    },
    {
      "inventory_id": "12076",
      "part_num": "32123b",
      "color_id": "14",
      "quantity": "4",
      "is_spare": "f",
      "img_url": "https://cdn.rebrickable.com/media/parts/elements/6271167.jpg",
      "name": "Technic Bush 1/2 Smooth with Axle Hole Semi-Reduced",
      "part_cat_id": "54",
      "part_material": "Plastic",
      "colorName": "Yellow"
    },
    {
      "inventory_id": "12076",
      "part_num": "3460",
      "color_id": "0",
      "quantity": "2",
      "is_spare": "f",
      "img_url": "https://cdn.rebrickable.com/media/parts/elements/346026.jpg",
      "name": "Plate 1 x 8",
      "part_cat_id": "14",
      "part_material": "Plastic",
      "colorName": "Black"
    },
    {
      "inventory_id": "12076",
      "part_num": "3622",
      "color_id": "0",
      "quantity": "2",
      "is_spare": "f",
      "img_url": "https://cdn.rebrickable.com/media/parts/elements/362226.jpg",
      "name": "Brick 1 x 3",
      "part_cat_id": "11",
      "part_material": "Plastic",
      "colorName": "Black"
    },
    {
      "inventory_id": "12076",
      "part_num": "3660",
      "color_id": "71",
      "quantity": "4",
      "is_spare": "f",
      "img_url": "https://cdn.rebrickable.com/media/parts/elements/4211436.jpg",
      "name": "Slope Inverted 45 2 x 2 [Ovoid Bottom Pin, Bar-sized Stud Holes]",
      "part_cat_id": "3",
      "part_material": "Plastic",
      "colorName": "Light Bluish Gray"
    },
    {
      "inventory_id": "12076",
      "part_num": "3666",
      "color_id": "0",
      "quantity": "3",
      "is_spare": "f",
      "img_url": "https://cdn.rebrickable.com/media/parts/elements/366626.jpg",
      "name": "Plate 1 x 6",
      "part_cat_id": "14",
      "part_material": "Plastic",
      "colorName": "Black"
    },
    {
      "inventory_id": "12076",
      "part_num": "3678b",
      "color_id": "4",
      "quantity": "1",
      "is_spare": "f",
      "img_url": "https://cdn.rebrickable.com/media/parts/elements/367821.jpg",
      "name": "Slope 65 2 x 2 x 2 with Bottom Tube",
      "part_cat_id": "3",
      "part_material": "Plastic",
      "colorName": "Red"
    },
    {
      "inventory_id": "12076",
      "part_num": "3700",
      "color_id": "4",
      "quantity": "3",
      "is_spare": "f",
      "img_url": "https://cdn.rebrickable.com/media/parts/elements/370021.jpg",
      "name": "Technic Brick 1 x 2 [1 Hole]",
      "part_cat_id": "8",
      "part_material": "Plastic",
      "colorName": "Red"
    },
    {
      "inventory_id": "12076",
      "part_num": "3701",
      "color_id": "0",
      "quantity": "2",
      "is_spare": "f",
      "img_url": "https://cdn.rebrickable.com/media/parts/elements/370126.jpg",
      "name": "Technic Brick 1 x 4 [3 Holes]",
      "part_cat_id": "8",
      "part_material": "Plastic",
      "colorName": "Black"
    },
    {
      "inventory_id": "12076",
      "part_num": "3702",
      "color_id": "71",
      "quantity": "2",
      "is_spare": "f",
      "img_url": "https://cdn.rebrickable.com/media/parts/elements/4211442.jpg",
      "name": "Technic Brick 1 x 8 [7 Holes]",
      "part_cat_id": "8",
      "part_material": "Plastic",
      "colorName": "Light Bluish Gray"
    },
    {
      "inventory_id": "12076",
      "part_num": "3707",
      "color_id": "0",
      "quantity": "2",
      "is_spare": "f",
      "img_url": "https://cdn.rebrickable.com/media/parts/elements/370726.jpg",
      "name": "Technic Axle 8",
      "part_cat_id": "46",
      "part_material": "Plastic",
      "colorName": "Black"
    },
    {
      "inventory_id": "12076",
      "part_num": "3710",
      "color_id": "15",
      "quantity": "1",
      "is_spare": "f",
      "img_url": "https://cdn.rebrickable.com/media/parts/elements/371001.jpg",
      "name": "Plate 1 x 4",
      "part_cat_id": "14",
      "part_material": "Plastic",
      "colorName": "White"
    },
    {
      "inventory_id": "12076",
      "part_num": "3710",
      "color_id": "71",
      "quantity": "3",
      "is_spare": "f",
      "img_url": "https://cdn.rebrickable.com/media/parts/elements/4211445.jpg",
      "name": "Plate 1 x 4",
      "part_cat_id": "14",
      "part_material": "Plastic",
      "colorName": "Light Bluish Gray"
    },
    {
      "inventory_id": "12076",
      "part_num": "3710",
      "color_id": "4",
      "quantity": "4",
      "is_spare": "f",
      "img_url": "https://cdn.rebrickable.com/media/parts/elements/371021.jpg",
      "name": "Plate 1 x 4",
      "part_cat_id": "14",
      "part_material": "Plastic",
      "colorName": "Red"
    },
    {
      "inventory_id": "12076",
      "part_num": "3710",
      "color_id": "0",
      "quantity": "4",
      "is_spare": "f",
      "img_url": "https://cdn.rebrickable.com/media/parts/elements/371026.jpg",
      "name": "Plate 1 x 4",
      "part_cat_id": "14",
      "part_material": "Plastic",
      "colorName": "Black"
    },
    {
      "inventory_id": "12076",
      "part_num": "3794b",
      "color_id": "0",
      "quantity": "1",
      "is_spare": "f",
      "img_url": "https://cdn.rebrickable.com/media/parts/elements/379426.jpg",
      "name": "Plate Special 1 x 2 with 1 Stud with Groove (Jumper)",
      "part_cat_id": "9",
      "part_material": "Plastic",
      "colorName": "Black"
    },
    {
      "inventory_id": "12076",
      "part_num": "3794b",
      "color_id": "297",
      "quantity": "2",
      "is_spare": "f",
      "img_url": "https://cdn.rebrickable.com/media/parts/elements/4523157.jpg",
      "name": "Plate Special 1 x 2 with 1 Stud with Groove (Jumper)",
      "part_cat_id": "9",
      "part_material": "Plastic",
      "colorName": "Pearl Gold"
    },
    {
      "inventory_id": "12076",
      "part_num": "3795",
      "color_id": "71",
      "quantity": "4",
      "is_spare": "f",
      "img_url": "https://cdn.rebrickable.com/media/parts/elements/4211452.jpg",
      "name": "Plate 2 x 6",
      "part_cat_id": "14",
      "part_material": "Plastic",
      "colorName": "Light Bluish Gray"
    },
    {
      "inventory_id": "12076",
      "part_num": "3832",
      "color_id": "71",
      "quantity": "2",
      "is_spare": "f",
      "img_url": "https://cdn.rebrickable.com/media/parts/elements/4211462.jpg",
      "name": "Plate 2 x 10",
      "part_cat_id": "14",
      "part_material": "Plastic",
      "colorName": "Light Bluish Gray"
    },
    {
      "inventory_id": "12076",
      "part_num": "3937",
      "color_id": "71",
      "quantity": "6",
      "is_spare": "f",
      "img_url": "https://cdn.rebrickable.com/media/parts/elements/4211469.jpg",
      "name": "Hinge Brick 1 x 2 Base",
      "part_cat_id": "18",
      "part_material": "Plastic",
      "colorName": "Light Bluish Gray"
    },
    {
      "inventory_id": "12076",
      "part_num": "3937",
      "color_id": "0",
      "quantity": "1",
      "is_spare": "f",
      "img_url": "https://cdn.rebrickable.com/media/parts/elements/393726.jpg",
      "name": "Hinge Brick 1 x 2 Base",
      "part_cat_id": "18",
      "part_material": "Plastic",
      "colorName": "Black"
    },
    {
      "inventory_id": "12076",
      "part_num": "3938",
      "color_id": "71",
      "quantity": "2",
      "is_spare": "f",
      "img_url": "https://cdn.rebrickable.com/media/parts/elements/4211470.jpg",
      "name": "Hinge Brick 1 x 2 Top Plate Thin",
      "part_cat_id": "18",
      "part_material": "Plastic",
      "colorName": "Light Bluish Gray"
    },
    {
      "inventory_id": "12076",
      "part_num": "3938",
      "color_id": "0",
      "quantity": "1",
      "is_spare": "f",
      "img_url": "https://cdn.rebrickable.com/media/parts/elements/393826.jpg",
      "name": "Hinge Brick 1 x 2 Top Plate Thin",
      "part_cat_id": "18",
      "part_material": "Plastic",
      "colorName": "Black"
    },
    {
      "inventory_id": "12076",
      "part_num": "3941",
      "color_id": "0",
      "quantity": "8",
      "is_spare": "f",
      "img_url": "https://cdn.rebrickable.com/media/parts/elements/614326.jpg",
      "name": "Brick Round 2 x 2 with Axle Hole",
      "part_cat_id": "20",
      "part_material": "Plastic",
      "colorName": "Black"
    },
    {
      "inventory_id": "12076",
      "part_num": "3942c",
      "color_id": "85",
      "quantity": "2",
      "is_spare": "f",
      "img_url": "https://cdn.rebrickable.com/media/parts/elements/4297454.jpg",
      "name": "Cone 2 x 2 x 2 with Completely Open Stud",
      "part_cat_id": "20",
      "part_material": "Plastic",
      "colorName": "Dark Purple"
    },
    {
      "inventory_id": "12076",
      "part_num": "4032a",
      "color_id": "72",
      "quantity": "2",
      "is_spare": "f",
      "img_url": "https://cdn.rebrickable.com/media/parts/elements/4211042.jpg",
      "name": "Plate Round 2 x 2 with Axle Hole Type 1 (+ Opening)",
      "part_cat_id": "21",
      "part_material": "Plastic",
      "colorName": "Dark Bluish Gray"
    },
    {
      "inventory_id": "12076",
      "part_num": "4032a",
      "color_id": "0",
      "quantity": "1",
      "is_spare": "f",
      "img_url": "https://cdn.rebrickable.com/media/parts/elements/403226.jpg",
      "name": "Plate Round 2 x 2 with Axle Hole Type 1 (+ Opening)",
      "part_cat_id": "21",
      "part_material": "Plastic",
      "colorName": "Black"
    },
    {
      "inventory_id": "12076",
      "part_num": "4081b",
      "color_id": "0",
      "quantity": "2",
      "is_spare": "f",
      "img_url": "https://cdn.rebrickable.com/media/parts/elements/408126.jpg",
      "name": "Plate Special 1 x 1 with Clip Light [Thick Ring]",
      "part_cat_id": "9",
      "part_material": "Plastic",
      "colorName": "Black"
    },
    {
      "inventory_id": "12076",
      "part_num": "4150",
      "color_id": "71",
      "quantity": "2",
      "is_spare": "f",
      "img_url": "https://cdn.rebrickable.com/media/parts/elements/4211480.jpg",
      "name": "Tile Round 2 x 2 with Bottom Cross",
      "part_cat_id": "67",
      "part_material": "Plastic",
      "colorName": "Light Bluish Gray"
    },
    {
      "inventory_id": "12076",
      "part_num": "4162",
      "color_id": "0",
      "quantity": "2",
      "is_spare": "f",
      "img_url": "https://cdn.rebrickable.com/media/parts/elements/416226.jpg",
      "name": "Tile 1 x 8 with Groove",
      "part_cat_id": "19",
      "part_material": "Plastic",
      "colorName": "Black"
    },
    {
      "inventory_id": "12076",
      "part_num": "41769",
      "color_id": "0",
      "quantity": "1",
      "is_spare": "f",
      "img_url": "https://cdn.rebrickable.com/media/parts/elements/4160869.jpg",
      "name": "Wedge Plate 4 x 2 Right",
      "part_cat_id": "49",
      "part_material": "Plastic",
      "colorName": "Black"
    },
    {
      "inventory_id": "12076",
      "part_num": "41770",
      "color_id": "0",
      "quantity": "1",
      "is_spare": "f",
      "img_url": "https://cdn.rebrickable.com/media/parts/elements/4161332.jpg",
      "name": "Wedge Plate 4 x 2 Left",
      "part_cat_id": "49",
      "part_material": "Plastic",
      "colorName": "Black"
    },
    {
      "inventory_id": "12076",
      "part_num": "41854",
      "color_id": "0",
      "quantity": "1",
      "is_spare": "f",
      "img_url": "https://cdn.rebrickable.com/media/parts/elements/4184813.jpg",
      "name": "Mudguard 2 x 4 with 2 x 2 Studs and Flared Wings",
      "part_cat_id": "36",
      "part_material": "Plastic",
      "colorName": "Black"
    },
    {
      "inventory_id": "12076",
      "part_num": "42023",
      "color_id": "0",
      "quantity": "2",
      "is_spare": "f",
      "img_url": "https://cdn.rebrickable.com/media/parts/elements/4160409.jpg",
      "name": "Brick Curved 6 x 1 Inverted",
      "part_cat_id": "37",
      "part_material": "Plastic",
      "colorName": "Black"
    },
    {
      "inventory_id": "12076",
      "part_num": "42445",
      "color_id": "71",
      "quantity": "2",
      "is_spare": "f",
      "img_url": "https://cdn.rebrickable.com/media/parts/elements/6277023.jpg",
      "name": "Bar 1 x 12 with 1 x 2 Plate End with Solid Studs and 1 x 1 Round Plate End",
      "part_cat_id": "32",
      "part_material": "Plastic",
      "colorName": "Light Bluish Gray"
    },
    {
      "inventory_id": "12076",
      "part_num": "4274",
      "color_id": "1",
      "quantity": "1",
      "is_spare": "f",
      "img_url": "https://cdn.rebrickable.com/media/parts/elements/4143005.jpg",
      "name": "Technic Pin 1/2",
      "part_cat_id": "53",
      "part_material": "Plastic",
      "colorName": "Blue"
    },
    {
      "inventory_id": "12076",
      "part_num": "43093",
      "color_id": "1",
      "quantity": "2",
      "is_spare": "f",
      "img_url": "https://cdn.rebrickable.com/media/parts/elements/4206482.jpg",
      "name": "Technic Axle Pin with Friction Ridges Lengthwise",
      "part_cat_id": "53",
      "part_material": "Plastic",
      "colorName": "Blue"
    },
    {
      "inventory_id": "12076",
      "part_num": "43337",
      "color_id": "46",
      "quantity": "4",
      "is_spare": "f",
      "img_url": "https://cdn.rebrickable.com/media/parts/elements/4581795.jpg",
      "name": "Panel 1 x 4 x 1 with Rounded Corners [Thick Wall]",
      "part_cat_id": "23",
      "part_material": "Plastic",
      "colorName": "Trans-Yellow"
    },
    {
      "inventory_id": "12076",
      "part_num": "43719",
      "color_id": "72",
      "quantity": "2",
      "is_spare": "f",
      "img_url": "https://cdn.rebrickable.com/media/parts/elements/4234938.jpg",
      "name": "Wedge Plate 4 x 4 with 2 x 2 Cutout",
      "part_cat_id": "49",
      "part_material": "Plastic",
      "colorName": "Dark Bluish Gray"
    },
    {
      "inventory_id": "12076",
      "part_num": "43722",
      "color_id": "0",
      "quantity": "1",
      "is_spare": "f",
      "img_url": "https://cdn.rebrickable.com/media/parts/elements/4180508.jpg",
      "name": "Wedge Plate 3 x 2 Right",
      "part_cat_id": "49",
      "part_material": "Plastic",
      "colorName": "Black"
    },
    {
      "inventory_id": "12076",
      "part_num": "43723",
      "color_id": "0",
      "quantity": "1",
      "is_spare": "f",
      "img_url": "https://cdn.rebrickable.com/media/parts/elements/4180536.jpg",
      "name": "Wedge Plate 3 x 2 Left",
      "part_cat_id": "49",
      "part_material": "Plastic",
      "colorName": "Black"
    },
    {
      "inventory_id": "12076",
      "part_num": "44126",
      "color_id": "0",
      "quantity": "2",
      "is_spare": "f",
      "img_url": "https://cdn.rebrickable.com/media/parts/elements/4180548.jpg",
      "name": "Brick Curved 6 x 2",
      "part_cat_id": "37",
      "part_material": "Plastic",
      "colorName": "Black"
    },
    {
      "inventory_id": "12076",
      "part_num": "44728",
      "color_id": "0",
      "quantity": "2",
      "is_spare": "f",
      "img_url": "https://cdn.rebrickable.com/media/parts/elements/4277932.jpg",
      "name": "Bracket 1 x 2 - 2 x 2",
      "part_cat_id": "9",
      "part_material": "Plastic",
      "colorName": "Black"
    },
    {
      "inventory_id": "12076",
      "part_num": "44728",
      "color_id": "71",
      "quantity": "2",
      "is_spare": "f",
      "img_url": "https://cdn.rebrickable.com/media/parts/elements/4277927.jpg",
      "name": "Bracket 1 x 2 - 2 x 2",
      "part_cat_id": "9",
      "part_material": "Plastic",
      "colorName": "Light Bluish Gray"
    },
    {
      "inventory_id": "12076",
      "part_num": "4477",
      "color_id": "0",
      "quantity": "8",
      "is_spare": "f",
      "img_url": "https://cdn.rebrickable.com/media/parts/elements/447726.jpg",
      "name": "Plate 1 x 10",
      "part_cat_id": "14",
      "part_material": "Plastic",
      "colorName": "Black"
    },
    {
      "inventory_id": "12076",
      "part_num": "4477",
      "color_id": "85",
      "quantity": "8",
      "is_spare": "f",
      "img_url": "https://cdn.rebrickable.com/media/parts/elements/4566532.jpg",
      "name": "Plate 1 x 10",
      "part_cat_id": "14",
      "part_material": "Plastic",
      "colorName": "Dark Purple"
    },
    {
      "inventory_id": "12076",
      "part_num": "45677",
      "color_id": "0",
      "quantity": "1",
      "is_spare": "f",
      "img_url": "https://cdn.rebrickable.com/media/parts/elements/4191191.jpg",
      "name": "Slope Curved 4 x 4 x 2/3 Triple Curved with 2 Studs",
      "part_cat_id": "37",
      "part_material": "Plastic",
      "colorName": "Black"
    },
    {
      "inventory_id": "12076",
      "part_num": "4623",
      "color_id": "0",
      "quantity": "1",
      "is_spare": "f",
      "img_url": "https://cdn.rebrickable.com/media/parts/elements/462326.jpg",
      "name": "Plate Special 1 x 2 with Arm Up [Horizontal Arm 6mm]",
      "part_cat_id": "9",
      "part_material": "Plastic",
      "colorName": "Black"
    },
    {
      "inventory_id": "12076",
      "part_num": "4733",
      "color_id": "0",
      "quantity": "2",
      "is_spare": "f",
      "img_url": "https://cdn.rebrickable.com/media/parts/elements/473326.jpg",
      "name": "Brick Special 1 x 1 Studs on 4 Sides",
      "part_cat_id": "5",
      "part_material": "Plastic",
      "colorName": "Black"
    },
    {
      "inventory_id": "12076",
      "part_num": "47457",
      "color_id": "297",
      "quantity": "1",
      "is_spare": "f",
      "img_url": "https://cdn.rebrickable.com/media/parts/elements/4286597.jpg",
      "name": "Brick Curved 2 x 2 x 2/3 Two Studs and Curved Slope End",
      "part_cat_id": "37",
      "part_material": "Plastic",
      "colorName": "Pearl Gold"
    },
    {
      "inventory_id": "12076",
      "part_num": "48336",
      "color_id": "0",
      "quantity": "2",
      "is_spare": "f",
      "img_url": "https://cdn.rebrickable.com/media/parts/elements/4225201.jpg",
      "name": "Plate Special 1 x 2 [Side Handle Closed Ends]",
      "part_cat_id": "9",
      "part_material": "Plastic",
      "colorName": "Black"
    },
    {
      "inventory_id": "12076",
      "part_num": "4865a",
      "color_id": "0",
      "quantity": "2",
      "is_spare": "f",
      "img_url": "https://cdn.rebrickable.com/media/parts/elements/486526.jpg",
      "name": "Panel 1 x 2 x 1 [Square Corners]",
      "part_cat_id": "23",
      "part_material": "Plastic",
      "colorName": "Black"
    },
    {
      "inventory_id": "12076",
      "part_num": "50943",
      "color_id": "297",
      "quantity": "1",
      "is_spare": "f",
      "img_url": "https://cdn.rebrickable.com/media/parts/elements/4584031.jpg",
      "name": "Engine / Air Scoop 2 x 2",
      "part_cat_id": "36",
      "part_material": "Plastic",
      "colorName": "Pearl Gold"
    },
    {
      "inventory_id": "12076",
      "part_num": "52031",
      "color_id": "0",
      "quantity": "2",
      "is_spare": "f",
      "img_url": "https://cdn.rebrickable.com/media/parts/elements/4500917.jpg",
      "name": "Slope Curved 4 x 6 x 2/3 Triple Curved with 4 Studs",
      "part_cat_id": "37",
      "part_material": "Plastic",
      "colorName": "Black"
    },
    {
      "inventory_id": "12076",
      "part_num": "52107",
      "color_id": "0",
      "quantity": "1",
      "is_spare": "f",
      "img_url": "https://cdn.rebrickable.com/media/parts/elements/4253815.jpg",
      "name": "Brick Special 1 x 2 with Studs on 2 Sides",
      "part_cat_id": "5",
      "part_material": "Plastic",
      "colorName": "Black"
    },
    {
      "inventory_id": "12076",
      "part_num": "54200",
      "color_id": "85",
      "quantity": "6",
      "is_spare": "f",
      "img_url": "https://cdn.rebrickable.com/media/parts/elements/4255409.jpg",
      "name": "Slope 30 1 x 1 x 2/3 (Cheese Slope)",
      "part_cat_id": "3",
      "part_material": "Plastic",
      "colorName": "Dark Purple"
    },
    {
      "inventory_id": "12076",
      "part_num": "54200",
      "color_id": "0",
      "quantity": "4",
      "is_spare": "f",
      "img_url": "https://cdn.rebrickable.com/media/parts/elements/4504382.jpg",
      "name": "Slope 30 1 x 1 x 2/3 (Cheese Slope)",
      "part_cat_id": "3",
      "part_material": "Plastic",
      "colorName": "Black"
    },
    {
      "inventory_id": "12076",
      "part_num": "55981",
      "color_id": "71",
      "quantity": "2",
      "is_spare": "f",
      "img_url": "https://cdn.rebrickable.com/media/parts/elements/4299119.jpg",
      "name": "Wheel 18 x 14 with Pin Hole, Fake Bolts and Shallow Spokes",
      "part_cat_id": "29",
      "part_material": "Plastic",
      "colorName": "Light Bluish Gray"
    },
    {
      "inventory_id": "12076",
      "part_num": "57028c01",
      "color_id": "71",
      "quantity": "1",
      "is_spare": "f",
      "img_url": "https://cdn.rebrickable.com/media/parts/elements/4299625.jpg",
      "name": "Projectile, Technic Competition Arrow, Liftarm Shaft with Hollow Black Rubber End",
      "part_cat_id": "68",
      "part_material": "Plastic",
      "colorName": "Light Bluish Gray"
    },
    {
      "inventory_id": "12076",
      "part_num": "57796",
      "color_id": "0",
      "quantity": "1",
      "is_spare": "f",
      "img_url": "https://cdn.rebrickable.com/media/parts/elements/4499434.jpg",
      "name": "Launcher, Technic Competition Cannon Flat Bottom [Complete Assembly]",
      "part_cat_id": "68",
      "part_material": "Plastic",
      "colorName": "Black"
    },
    {
      "inventory_id": "12076",
      "part_num": "59900",
      "color_id": "36",
      "quantity": "4",
      "is_spare": "f",
      "img_url": "https://cdn.rebrickable.com/media/parts/elements/4544720.jpg",
      "name": "Cone 1 x 1 [Top Groove]",
      "part_cat_id": "20",
      "part_material": "Plastic",
      "colorName": "Trans-Red"
    },
    {
      "inventory_id": "12076",
      "part_num": "59900",
      "color_id": "46",
      "quantity": "2",
      "is_spare": "f",
      "img_url": "https://cdn.rebrickable.com/media/parts/elements/4567332.jpg",
      "name": "Cone 1 x 1 [Top Groove]",
      "part_cat_id": "20",
      "part_material": "Plastic",
      "colorName": "Trans-Yellow"
    },
    {
      "inventory_id": "12076",
      "part_num": "59900",
      "color_id": "297",
      "quantity": "3",
      "is_spare": "f",
      "img_url": "https://cdn.rebrickable.com/media/parts/elements/4529247.jpg",
      "name": "Cone 1 x 1 [Top Groove]",
      "part_cat_id": "20",
      "part_material": "Plastic",
      "colorName": "Pearl Gold"
    },
    {
      "inventory_id": "12076",
      "part_num": "6019",
      "color_id": "297",
      "quantity": "1",
      "is_spare": "f",
      "img_url": "https://cdn.rebrickable.com/media/parts/ldraw/297/6019.png",
      "name": "Plate Special 1 x 1 with Clip Horizontal [Thick U Clip]",
      "part_cat_id": "9",
      "part_material": "Plastic",
      "colorName": "Pearl Gold"
    },
    {
      "inventory_id": "12076",
      "part_num": "60470a",
      "color_id": "0",
      "quantity": "4",
      "is_spare": "f",
      "img_url": "https://cdn.rebrickable.com/media/parts/ldraw/0/60470a.png",
      "name": "Plate Special 1 x 2 with Clips Horizontal [Thick U-Clips]",
      "part_cat_id": "9",
      "part_material": "Plastic",
      "colorName": "Black"
    },
    {
      "inventory_id": "12076",
      "part_num": "60478",
      "color_id": "71",
      "quantity": "2",
      "is_spare": "f",
      "img_url": "https://cdn.rebrickable.com/media/parts/elements/4515369.jpg",
      "name": "Plate Special 1 x 2 with Handle on End [Closed Ends]",
      "part_cat_id": "9",
      "part_material": "Plastic",
      "colorName": "Light Bluish Gray"
    },
    {
      "inventory_id": "12076",
      "part_num": "6091",
      "color_id": "4",
      "quantity": "2",
      "is_spare": "f",
      "img_url": "https://cdn.rebrickable.com/media/parts/elements/609121.jpg",
      "name": "Brick Curved 1 x 2 x 1 1/3 with Curved Top",
      "part_cat_id": "37",
      "part_material": "Plastic",
      "colorName": "Red"
    },
    {
      "inventory_id": "12076",
      "part_num": "6091",
      "color_id": "0",
      "quantity": "2",
      "is_spare": "f",
      "img_url": "https://cdn.rebrickable.com/media/parts/elements/609126.jpg",
      "name": "Brick Curved 1 x 2 x 1 1/3 with Curved Top",
      "part_cat_id": "37",
      "part_material": "Plastic",
      "colorName": "Black"
    },
    {
      "inventory_id": "12076",
      "part_num": "6111",
      "color_id": "72",
      "quantity": "2",
      "is_spare": "f",
      "img_url": "https://cdn.rebrickable.com/media/parts/elements/4211107.jpg",
      "name": "Brick 1 x 10",
      "part_cat_id": "11",
      "part_material": "Plastic",
      "colorName": "Dark Bluish Gray"
    },
    {
      "inventory_id": "12076",
      "part_num": "6112",
      "color_id": "0",
      "quantity": "2",
      "is_spare": "f",
      "img_url": "https://cdn.rebrickable.com/media/parts/elements/611226.jpg",
      "name": "Brick 1 x 12",
      "part_cat_id": "11",
      "part_material": "Plastic",
      "colorName": "Black"
    },
    {
      "inventory_id": "12076",
      "part_num": "6134",
      "color_id": "0",
      "quantity": "4",
      "is_spare": "f",
      "img_url": "https://cdn.rebrickable.com/media/parts/elements/4124096.jpg",
      "name": "Hinge Brick 2 x 2 Top Plate Thin",
      "part_cat_id": "18",
      "part_material": "Plastic",
      "colorName": "Black"
    },
    {
      "inventory_id": "12076",
      "part_num": "61409",
      "color_id": "0",
      "quantity": "2",
      "is_spare": "f",
      "img_url": "https://cdn.rebrickable.com/media/parts/elements/4541191.jpg",
      "name": "Slope 18 2 x 1 x 2/3 with 4 Slots",
      "part_cat_id": "3",
      "part_material": "Plastic",
      "colorName": "Black"
    },
    {
      "inventory_id": "12076",
      "part_num": "6141",
      "color_id": "297",
      "quantity": "27",
      "is_spare": "f",
      "img_url": "https://cdn.rebrickable.com/media/parts/elements/4523159.jpg",
      "name": "Plate Round 1 x 1 with Solid Stud",
      "part_cat_id": "21",
      "part_material": "Plastic",
      "colorName": "Pearl Gold"
    },
    {
      "inventory_id": "12076",
      "part_num": "6141",
      "color_id": "34",
      "quantity": "1",
      "is_spare": "f",
      "img_url": "https://cdn.rebrickable.com/media/parts/elements/3005748.jpg",
      "name": "Plate Round 1 x 1 with Solid Stud",
      "part_cat_id": "21",
      "part_material": "Plastic",
      "colorName": "Trans-Green"
    },
    {
      "inventory_id": "12076",
      "part_num": "6141",
      "color_id": "47",
      "quantity": "4",
      "is_spare": "f",
      "img_url": "https://cdn.rebrickable.com/media/parts/elements/3005740.jpg",
      "name": "Plate Round 1 x 1 with Solid Stud",
      "part_cat_id": "21",
      "part_material": "Plastic",
      "colorName": "Trans-Clear"
    },
    {
      "inventory_id": "12076",
      "part_num": "61678",
      "color_id": "0",
      "quantity": "8",
      "is_spare": "f",
      "img_url": "https://cdn.rebrickable.com/media/parts/elements/4522034.jpg",
      "name": "Slope Curved 4 x 1 No Studs [Stud Holder with Asymmetric Ridges]",
      "part_cat_id": "37",
      "part_material": "Plastic",
      "colorName": "Black"
    },
    {
      "inventory_id": "12076",
      "part_num": "6180",
      "color_id": "0",
      "quantity": "1",
      "is_spare": "f",
      "img_url": "https://cdn.rebrickable.com/media/parts/elements/4100378.jpg",
      "name": "Plate Special 4 x 6 with Studs on 3 Edges",
      "part_cat_id": "9",
      "part_material": "Plastic",
      "colorName": "Black"
    },
    {
      "inventory_id": "12076",
      "part_num": "62360",
      "color_id": "46",
      "quantity": "1",
      "is_spare": "f",
      "img_url": "https://cdn.rebrickable.com/media/parts/elements/4581798.jpg",
      "name": "Windscreen 3 x 6 x 1 Curved with 2 Circular Stud Holders in Bottom",
      "part_cat_id": "47",
      "part_material": "Plastic",
      "colorName": "Trans-Yellow"
    },
    {
      "inventory_id": "12076",
      "part_num": "62361",
      "color_id": "0",
      "quantity": "6",
      "is_spare": "f",
      "img_url": "https://cdn.rebrickable.com/media/parts/elements/4547625.jpg",
      "name": "Wheel Arch, Mudguard, 1 1/2 x 6 x 1 [Arch Extended]",
      "part_cat_id": "36",
      "part_material": "Plastic",
      "colorName": "Black"
    },
    {
      "inventory_id": "12076",
      "part_num": "6239",
      "color_id": "0",
      "quantity": "6",
      "is_spare": "f",
      "img_url": "https://cdn.rebrickable.com/media/parts/elements/4113850.jpg",
      "name": "Tail Shuttle",
      "part_cat_id": "35",
      "part_material": "Plastic",
      "colorName": "Black"
    },
    {
      "inventory_id": "12076",
      "part_num": "64727",
      "color_id": "71",
      "quantity": "2",
      "is_spare": "f",
      "img_url": "https://cdn.rebrickable.com/media/parts/elements/4616840.jpg",
      "name": "Weapon Spike Flexible 3.5L",
      "part_cat_id": "27",
      "part_material": "Plastic",
      "colorName": "Light Bluish Gray"
    },
    {
      "inventory_id": "12076",
      "part_num": "6636",
      "color_id": "0",
      "quantity": "3",
      "is_spare": "f",
      "img_url": "https://cdn.rebrickable.com/media/parts/elements/663626.jpg",
      "name": "Tile 1 x 6 with Groove",
      "part_cat_id": "19",
      "part_material": "Plastic",
      "colorName": "Black"
    },
    {
      "inventory_id": "12076",
      "part_num": "85970",
      "color_id": "0",
      "quantity": "4",
      "is_spare": "f",
      "img_url": "https://cdn.rebrickable.com/media/parts/elements/4567440.jpg",
      "name": "Brick Curved 10 x 1 [Asymmetric Inside Ridges]",
      "part_cat_id": "37",
      "part_material": "Plastic",
      "colorName": "Black"
    },
    {
      "inventory_id": "12076",
      "part_num": "86208",
      "color_id": "72",
      "quantity": "1",
      "is_spare": "f",
      "img_url": "https://cdn.rebrickable.com/media/parts/elements/4566028.jpg",
      "name": "Weapon Gun / Torch (Space) [No Grooves]",
      "part_cat_id": "27",
      "part_material": "Plastic",
      "colorName": "Dark Bluish Gray"
    },
    {
      "inventory_id": "12076",
      "part_num": "87079",
      "color_id": "0",
      "quantity": "2",
      "is_spare": "f",
      "img_url": "https://cdn.rebrickable.com/media/parts/elements/4560182.jpg",
      "name": "Tile 2 x 4 with Groove",
      "part_cat_id": "19",
      "part_material": "Plastic",
      "colorName": "Black"
    },
    {
      "inventory_id": "12076",
      "part_num": "87087",
      "color_id": "0",
      "quantity": "4",
      "is_spare": "f",
      "img_url": "https://cdn.rebrickable.com/media/parts/elements/4558954.jpg",
      "name": "Brick Special 1 x 1 with Stud on 1 Side",
      "part_cat_id": "5",
      "part_material": "Plastic",
      "colorName": "Black"
    },
    {
      "inventory_id": "12076",
      "part_num": "90322",
      "color_id": "297",
      "quantity": "1",
      "is_spare": "f",
      "img_url": "https://cdn.rebrickable.com/media/parts/elements/4586584.jpg",
      "name": "Minifig Head Special with Jagged Bottom Edge [Plain]",
      "part_cat_id": "59",
      "part_material": "Plastic",
      "colorName": "Pearl Gold"
    },
    {
      "inventory_id": "12076",
      "part_num": "90784",
      "color_id": "9999",
      "quantity": "1",
      "is_spare": "f",
      "img_url": "",
      "name": "Sticker Sheet for Set 5984-1",
      "part_cat_id": "58",
      "part_material": "Plastic",
      "colorName": "[No Color/Any Color]"
    }
  ],
  "spareParts": [
    {
      "inventory_id": "12076",
      "part_num": "2447",
      "color_id": "36",
      "quantity": "1",
      "is_spare": "t",
      "img_url": "https://cdn.rebrickable.com/media/parts/elements/4569898.jpg",
      "name": "Headwear Accessory Visor For Standard Helmet",
      "part_cat_id": "27",
      "part_material": "Plastic",
      "colorName": "Trans-Red"
    },
    {
      "inventory_id": "12076",
      "part_num": "2569",
      "color_id": "0",
      "quantity": "1",
      "is_spare": "t",
      "img_url": "https://cdn.rebrickable.com/media/parts/elements/256926.jpg",
      "name": "Antenna Whip 8H",
      "part_cat_id": "32",
      "part_material": "Plastic",
      "colorName": "Black"
    },
    {
      "inventory_id": "12076",
      "part_num": "2780",
      "color_id": "0",
      "quantity": "2",
      "is_spare": "t",
      "img_url": "https://cdn.rebrickable.com/media/parts/elements/4121715.jpg",
      "name": "Technic Pin with Friction Ridges Lengthwise and Center Slots",
      "part_cat_id": "53",
      "part_material": "Plastic",
      "colorName": "Black"
    },
    {
      "inventory_id": "12076",
      "part_num": "298c02",
      "color_id": "71",
      "quantity": "1",
      "is_spare": "t",
      "img_url": "https://cdn.rebrickable.com/media/parts/elements/4221775.jpg",
      "name": "Lever Small Base with Black Lever",
      "part_cat_id": "32",
      "part_material": "Plastic",
      "colorName": "Light Bluish Gray"
    },
    {
      "inventory_id": "12076",
      "part_num": "32002",
      "color_id": "72",
      "quantity": "1",
      "is_spare": "t",
      "img_url": "https://cdn.rebrickable.com/media/parts/elements/4211050.jpg",
      "name": "Technic Pin 3/4",
      "part_cat_id": "53",
      "part_material": "Plastic",
      "colorName": "Dark Bluish Gray"
    },
    {
      "inventory_id": "12076",
      "part_num": "32123b",
      "color_id": "14",
      "quantity": "1",
      "is_spare": "t",
      "img_url": "https://cdn.rebrickable.com/media/parts/elements/6271167.jpg",
      "name": "Technic Bush 1/2 Smooth with Axle Hole Semi-Reduced",
      "part_cat_id": "54",
      "part_material": "Plastic",
      "colorName": "Yellow"
    },
    {
      "inventory_id": "12076",
      "part_num": "4274",
      "color_id": "1",
      "quantity": "1",
      "is_spare": "t",
      "img_url": "https://cdn.rebrickable.com/media/parts/elements/4143005.jpg",
      "name": "Technic Pin 1/2",
      "part_cat_id": "53",
      "part_material": "Plastic",
      "colorName": "Blue"
    },
    {
      "inventory_id": "12076",
      "part_num": "54200",
      "color_id": "85",
      "quantity": "2",
      "is_spare": "t",
      "img_url": "https://cdn.rebrickable.com/media/parts/elements/4255409.jpg",
      "name": "Slope 30 1 x 1 x 2/3 (Cheese Slope)",
      "part_cat_id": "3",
      "part_material": "Plastic",
      "colorName": "Dark Purple"
    },
    {
      "inventory_id": "12076",
      "part_num": "54200",
      "color_id": "0",
      "quantity": "1",
      "is_spare": "t",
      "img_url": "https://cdn.rebrickable.com/media/parts/elements/4504382.jpg",
      "name": "Slope 30 1 x 1 x 2/3 (Cheese Slope)",
      "part_cat_id": "3",
      "part_material": "Plastic",
      "colorName": "Black"
    },
    {
      "inventory_id": "12076",
      "part_num": "6141",
      "color_id": "34",
      "quantity": "1",
      "is_spare": "t",
      "img_url": "https://cdn.rebrickable.com/media/parts/elements/3005748.jpg",
      "name": "Plate Round 1 x 1 with Solid Stud",
      "part_cat_id": "21",
      "part_material": "Plastic",
      "colorName": "Trans-Green"
    },
    {
      "inventory_id": "12076",
      "part_num": "6141",
      "color_id": "297",
      "quantity": "4",
      "is_spare": "t",
      "img_url": "https://cdn.rebrickable.com/media/parts/elements/4523159.jpg",
      "name": "Plate Round 1 x 1 with Solid Stud",
      "part_cat_id": "21",
      "part_material": "Plastic",
      "colorName": "Pearl Gold"
    },
    {
      "inventory_id": "12076",
      "part_num": "6141",
      "color_id": "47",
      "quantity": "1",
      "is_spare": "t",
      "img_url": "https://cdn.rebrickable.com/media/parts/elements/3005740.jpg",
      "name": "Plate Round 1 x 1 with Solid Stud",
      "part_cat_id": "21",
      "part_material": "Plastic",
      "colorName": "Trans-Clear"
    }
  ],
  "setInfo": {
    "set_num": "5984-1",
    "name": "Lunar Limo",
    "year": "2010",
    "theme_id": "141",
    "num_parts": "391",
    "img_url": "https://cdn.rebrickable.com/media/sets/5984-1.jpg"
  },
  "countedUniqueParts": 142,
  "countedSpareParts": 17,
  "countedStandardParts": 378,
  "minfigSetParts": [
    [
      {
        "inventory_id": "53080",
        "part_num": "61506",
        "color_id": "85",
        "quantity": "1",
        "is_spare": "f",
        "img_url": "https://cdn.rebrickable.com/media/parts/elements/4587043.jpg",
        "name": "Hat Wide Brim, Outback Style with Wide Belt, Buckle (Fedora)",
        "part_cat_id": "65",
        "part_material": "Plastic",
        "colorName": "Dark Purple",
        "fig_num": "fig-002253"
      },
      {
        "inventory_id": "53080",
        "part_num": "90322pr0001",
        "color_id": "294",
        "quantity": "1",
        "is_spare": "f",
        "img_url": "https://cdn.rebrickable.com/media/parts/elements/4584753.jpg",
        "name": "Minifig Head Special with Jagged Bottom Edge and Eyes Print (Brick Daddy)",
        "part_cat_id": "59",
        "part_material": "Plastic",
        "colorName": "Glow In Dark Trans",
        "fig_num": "fig-002253"
      },
      {
        "inventory_id": "53080",
        "part_num": "970c09",
        "color_id": "85",
        "quantity": "1",
        "is_spare": "f",
        "img_url": "https://cdn.rebrickable.com/media/parts/elements/4226866.jpg",
        "name": "Hips and Dark Purple Legs",
        "part_cat_id": "61",
        "part_material": "Plastic",
        "colorName": "Dark Purple",
        "fig_num": "fig-002253"
      },
      {
        "inventory_id": "53080",
        "part_num": "973c09h03pr9918",
        "color_id": "85",
        "quantity": "1",
        "is_spare": "f",
        "img_url": "https://cdn.rebrickable.com/media/parts/elements/4585647.jpg",
        "name": "Torso Jacket with Pockets and Gold Necklace with Skull Pendant Print, Dark Purple Arms, Black Hands",
        "part_cat_id": "60",
        "part_material": "Plastic",
        "colorName": "Dark Purple",
        "fig_num": "fig-002253"
      }
    ],
    [
      {
        "inventory_id": "53081",
        "part_num": "92555pr0001",
        "color_id": "379",
        "quantity": "1",
        "is_spare": "f",
        "img_url": "https://cdn.rebrickable.com/media/parts/elements/4595276.jpg",
        "name": "Minifig Head Special, Henchman Creature with Fins (Jawson)",
        "part_cat_id": "59",
        "part_material": "Plastic",
        "colorName": "Sand Blue",
        "fig_num": "fig-002254"
      },
      {
        "inventory_id": "53081",
        "part_num": "970c34pr0159",
        "color_id": "25",
        "quantity": "1",
        "is_spare": "f",
        "img_url": "https://cdn.rebrickable.com/media/parts/elements/4586113.jpg",
        "name": "Hips and Orange Legs with Button on Hips, File in Pocket and '245633' Print",
        "part_cat_id": "61",
        "part_material": "Plastic",
        "colorName": "Orange",
        "fig_num": "fig-002254"
      },
      {
        "inventory_id": "53081",
        "part_num": "973c34h12pr1638",
        "color_id": "25",
        "quantity": "1",
        "is_spare": "f",
        "img_url": "https://cdn.rebrickable.com/media/parts/elements/4585877.jpg",
        "name": "Torso '245633' and Barcode Print, Orange Arms, Dark Bluish Gray Hands",
        "part_cat_id": "60",
        "part_material": "Plastic",
        "colorName": "Orange",
        "fig_num": "fig-002254"
      }
    ],
    [
      {
        "inventory_id": "53082",
        "part_num": "2447",
        "color_id": "36",
        "quantity": "1",
        "is_spare": "f",
        "img_url": "https://cdn.rebrickable.com/media/parts/elements/4569898.jpg",
        "name": "Headwear Accessory Visor For Standard Helmet",
        "part_cat_id": "27",
        "part_material": "Plastic",
        "colorName": "Trans-Red",
        "fig_num": "fig-002255"
      },
      {
        "inventory_id": "53082",
        "part_num": "3626bpr0500",
        "color_id": "14",
        "quantity": "1",
        "is_spare": "f",
        "img_url": "https://cdn.rebrickable.com/media/parts/ldraw/14/3626bp8h.png",
        "name": "Minifig Head, Eyebrows, Crows Feet with Open Mouth Scared / Mischievous Print",
        "part_cat_id": "59",
        "part_material": "Plastic",
        "colorName": "Yellow",
        "fig_num": "fig-002255"
      },
      {
        "inventory_id": "53082",
        "part_num": "3838",
        "color_id": "0",
        "quantity": "1",
        "is_spare": "f",
        "img_url": "https://cdn.rebrickable.com/media/parts/elements/383826.jpg",
        "name": "Minifig Neckwear Airtanks",
        "part_cat_id": "27",
        "part_material": "Plastic",
        "colorName": "Black",
        "fig_num": "fig-002255"
      },
      {
        "inventory_id": "53082",
        "part_num": "87781",
        "color_id": "72",
        "quantity": "1",
        "is_spare": "f",
        "img_url": "https://cdn.rebrickable.com/media/parts/elements/4568359.jpg",
        "name": "Helmet Space",
        "part_cat_id": "65",
        "part_material": "Plastic",
        "colorName": "Dark Bluish Gray",
        "fig_num": "fig-002255"
      },
      {
        "inventory_id": "53082",
        "part_num": "970c12pr0127",
        "color_id": "72",
        "quantity": "1",
        "is_spare": "f",
        "img_url": "https://cdn.rebrickable.com/media/parts/elements/4551179.jpg",
        "name": "Hips and Dark Bluish Gray Legs with Space Police 3 Pockets Print",
        "part_cat_id": "61",
        "part_material": "Plastic",
        "colorName": "Dark Bluish Gray",
        "fig_num": "fig-002255"
      },
      {
        "inventory_id": "53082",
        "part_num": "973c12h03pr1490",
        "color_id": "72",
        "quantity": "1",
        "is_spare": "f",
        "img_url": "https://cdn.rebrickable.com/media/parts/elements/4551188.jpg",
        "name": "Torso Spacesuit with Red Police Badge, Belt with Pouches / Radio on Back Print, Dark Bluish Gray Arms, Black Hands",
        "part_cat_id": "60",
        "part_material": "Plastic",
        "colorName": "Dark Bluish Gray",
        "fig_num": "fig-002255"
      }
    ]
  ]
}