{
  "standard": [
    {
      "inventory_id": "42622",
      "part_num": "10197",
      "color_id": "0",
      "quantity": "1",
      "is_spare": "f",
      "img_url": "https://cdn.rebrickable.com/media/parts/elements/6099801.jpg",
      "name": "Technic Pin Connector Hub with 2 Perpendicular Axles",
      "part_cat_id": "12",
      "part_material": "Plastic",
      "colorName": "Black"
    },
    {
      "inventory_id": "42622",
      "part_num": "11090",
      "color_id": "70",
      "quantity": "1",
      "is_spare": "f",
      "img_url": "https://cdn.rebrickable.com/media/parts/elements/6080355.jpg",
      "name": "Bar Holder with Clip",
      "part_cat_id": "32",
      "part_material": "Plastic",
      "colorName": "Reddish Brown"
    },
    {
      "inventory_id": "42622",
      "part_num": "11203",
      "color_id": "71",
      "quantity": "4",
      "is_spare": "f",
      "img_url": "https://cdn.rebrickable.com/media/parts/elements/6132886.jpg",
      "name": "Tile Special 2 x 2 Inverted",
      "part_cat_id": "15",
      "part_material": "Plastic",
      "colorName": "Light Bluish Gray"
    },
    {
      "inventory_id": "42622",
      "part_num": "11212",
      "color_id": "72",
      "quantity": "2",
      "is_spare": "f",
      "img_url": "https://cdn.rebrickable.com/media/parts/elements/6039176.jpg",
      "name": "Plate 3 x 3",
      "part_cat_id": "14",
      "part_material": "Plastic",
      "colorName": "Dark Bluish Gray"
    },
    {
      "inventory_id": "42622",
      "part_num": "11458",
      "color_id": "72",
      "quantity": "3",
      "is_spare": "f",
      "img_url": "https://cdn.rebrickable.com/media/parts/elements/6019987.jpg",
      "name": "Plate Special 1 x 2 with Pin Hole on Top",
      "part_cat_id": "9",
      "part_material": "Plastic",
      "colorName": "Dark Bluish Gray"
    },
    {
      "inventory_id": "42622",
      "part_num": "15397",
      "color_id": "70",
      "quantity": "1",
      "is_spare": "f",
      "img_url": "https://cdn.rebrickable.com/media/parts/elements/6050918.jpg",
      "name": "Plate 3 x 3 Cross",
      "part_cat_id": "14",
      "part_material": "Plastic",
      "colorName": "Reddish Brown"
    },
    {
      "inventory_id": "42622",
      "part_num": "15573",
      "color_id": "71",
      "quantity": "3",
      "is_spare": "f",
      "img_url": "https://cdn.rebrickable.com/media/parts/elements/4211451.jpg",
      "name": "Plate Special 1 x 2 with 1 Stud with Groove and Inside Stud Holder (Jumper)",
      "part_cat_id": "9",
      "part_material": "Plastic",
      "colorName": "Light Bluish Gray"
    },
    {
      "inventory_id": "42622",
      "part_num": "15573",
      "color_id": "28",
      "quantity": "17",
      "is_spare": "f",
      "img_url": "https://cdn.rebrickable.com/media/parts/elements/6092591.jpg",
      "name": "Plate Special 1 x 2 with 1 Stud with Groove and Inside Stud Holder (Jumper)",
      "part_cat_id": "9",
      "part_material": "Plastic",
      "colorName": "Dark Tan"
    },
    {
      "inventory_id": "42622",
      "part_num": "15712",
      "color_id": "72",
      "quantity": "1",
      "is_spare": "f",
      "img_url": "https://cdn.rebrickable.com/media/parts/elements/6071226.jpg",
      "name": "Tile Special 1 x 1 with Clip with Rounded Edges",
      "part_cat_id": "15",
      "part_material": "Plastic",
      "colorName": "Dark Bluish Gray"
    },
    {
      "inventory_id": "42622",
      "part_num": "15712",
      "color_id": "297",
      "quantity": "1",
      "is_spare": "f",
      "img_url": "https://cdn.rebrickable.com/media/parts/elements/6071259.jpg",
      "name": "Tile Special 1 x 1 with Clip with Rounded Edges",
      "part_cat_id": "15",
      "part_material": "Plastic",
      "colorName": "Pearl Gold"
    },
    {
      "inventory_id": "42622",
      "part_num": "18651",
      "color_id": "0",
      "quantity": "2",
      "is_spare": "f",
      "img_url": "https://cdn.rebrickable.com/media/parts/elements/6089119.jpg",
      "name": "Technic Axle Pin 3L with Friction Ridges Lengthwise and 2L Axle",
      "part_cat_id": "53",
      "part_material": "Plastic",
      "colorName": "Black"
    },
    {
      "inventory_id": "42622",
      "part_num": "18677",
      "color_id": "70",
      "quantity": "2",
      "is_spare": "f",
      "img_url": "https://cdn.rebrickable.com/media/parts/elements/6192310.jpg",
      "name": "Plate Special 1 x 2 with Pin Hole Underneath",
      "part_cat_id": "9",
      "part_material": "Plastic",
      "colorName": "Reddish Brown"
    },
    {
      "inventory_id": "42622",
      "part_num": "18787",
      "color_id": "322",
      "quantity": "1",
      "is_spare": "f",
      "img_url": "https://cdn.rebrickable.com/media/parts/elements/6093623.jpg",
      "name": "Weapon Sword Blocky",
      "part_cat_id": "27",
      "part_material": "Plastic",
      "colorName": "Medium Azure"
    },
    {
      "inventory_id": "42622",
      "part_num": "18788",
      "color_id": "179",
      "quantity": "1",
      "is_spare": "f",
      "img_url": "https://cdn.rebrickable.com/media/parts/elements/6089099.jpg",
      "name": "Weapon Axe Blocky",
      "part_cat_id": "27",
      "part_material": "Plastic",
      "colorName": "Flat Silver"
    },
    {
      "inventory_id": "42622",
      "part_num": "18792",
      "color_id": "70",
      "quantity": "1",
      "is_spare": "f",
      "img_url": "https://cdn.rebrickable.com/media/parts/elements/6089103.jpg",
      "name": "Weapon Bow and Arrow, Blocky",
      "part_cat_id": "27",
      "part_material": "Plastic",
      "colorName": "Reddish Brown"
    },
    {
      "inventory_id": "42622",
      "part_num": "19119",
      "color_id": "484",
      "quantity": "3",
      "is_spare": "f",
      "img_url": "https://cdn.rebrickable.com/media/parts/elements/6151196.jpg",
      "name": "Plant, Flower Stem with Bar and 6 Stems",
      "part_cat_id": "28",
      "part_material": "Plastic",
      "colorName": "Dark Orange"
    },
    {
      "inventory_id": "42622",
      "part_num": "19723",
      "color_id": "322",
      "quantity": "1",
      "is_spare": "f",
      "img_url": "https://cdn.rebrickable.com/media/parts/elements/6101979.jpg",
      "name": "Minifig Neckwear Armour Breastplate Rectangular (Minecraft)",
      "part_cat_id": "27",
      "part_material": "Plastic",
      "colorName": "Medium Azure"
    },
    {
      "inventory_id": "42622",
      "part_num": "19727pr0002",
      "color_id": "29",
      "quantity": "1",
      "is_spare": "f",
      "img_url": "https://cdn.rebrickable.com/media/parts/elements/6103108.jpg",
      "name": "Minifig Head Special, Cube with Rear Ledge, Pixelated Black, White and Dark Red Face Print (Pig)",
      "part_cat_id": "59",
      "part_material": "Plastic",
      "colorName": "Bright Pink"
    },
    {
      "inventory_id": "42622",
      "part_num": "19729",
      "color_id": "19",
      "quantity": "1",
      "is_spare": "f",
      "img_url": "https://cdn.rebrickable.com/media/parts/elements/6265236.jpg",
      "name": "Minifig Head Special, Cube [Plain]",
      "part_cat_id": "59",
      "part_material": "Plastic",
      "colorName": "Tan"
    },
    {
      "inventory_id": "42622",
      "part_num": "19730",
      "color_id": "322",
      "quantity": "1",
      "is_spare": "f",
      "img_url": "https://cdn.rebrickable.com/media/parts/elements/6101987.jpg",
      "name": "Helmet Rectangular",
      "part_cat_id": "65",
      "part_material": "Plastic",
      "colorName": "Medium Azure"
    },
    {
      "inventory_id": "42622",
      "part_num": "20482",
      "color_id": "47",
      "quantity": "2",
      "is_spare": "f",
      "img_url": "https://cdn.rebrickable.com/media/parts/elements/6112751.jpg",
      "name": "Tile Round 1 x 1 with Hollow Bar",
      "part_cat_id": "15",
      "part_material": "Plastic",
      "colorName": "Trans-Clear"
    },
    {
      "inventory_id": "42622",
      "part_num": "24008pr0004",
      "color_id": "15",
      "quantity": "1",
      "is_spare": "f",
      "img_url": "https://cdn.rebrickable.com/media/parts/elements/6290443.jpg",
      "name": "Animal Body Part, Cat Head 1 x 2 with Cube with Ears, Nose and Pixelated Face with 1 Blue Eye and 1 Black Eye and Orange Patch print (Cat)",
      "part_cat_id": "28",
      "part_material": "Plastic",
      "colorName": "White"
    },
    {
      "inventory_id": "42622",
      "part_num": "2431",
      "color_id": "28",
      "quantity": "3",
      "is_spare": "f",
      "img_url": "https://cdn.rebrickable.com/media/parts/elements/6175927.jpg",
      "name": "Tile 1 x 4 with Groove",
      "part_cat_id": "19",
      "part_material": "Plastic",
      "colorName": "Dark Tan"
    },
    {
      "inventory_id": "42622",
      "part_num": "2445",
      "color_id": "19",
      "quantity": "1",
      "is_spare": "f",
      "img_url": "https://cdn.rebrickable.com/media/parts/elements/4113985.jpg",
      "name": "Plate 2 x 12",
      "part_cat_id": "14",
      "part_material": "Plastic",
      "colorName": "Tan"
    },
    {
      "inventory_id": "42622",
      "part_num": "2453b",
      "color_id": "19",
      "quantity": "4",
      "is_spare": "f",
      "img_url": "https://cdn.rebrickable.com/media/parts/elements/4112980.jpg",
      "name": "Brick 1 x 1 x 5 with Solid Stud",
      "part_cat_id": "11",
      "part_material": "Plastic",
      "colorName": "Tan"
    },
    {
      "inventory_id": "42622",
      "part_num": "2456",
      "color_id": "19",
      "quantity": "2",
      "is_spare": "f",
      "img_url": "https://cdn.rebrickable.com/media/parts/elements/4143256.jpg",
      "name": "Brick 2 x 6",
      "part_cat_id": "11",
      "part_material": "Plastic",
      "colorName": "Tan"
    },
    {
      "inventory_id": "42622",
      "part_num": "2456",
      "color_id": "70",
      "quantity": "2",
      "is_spare": "f",
      "img_url": "https://cdn.rebrickable.com/media/parts/elements/4216615.jpg",
      "name": "Brick 2 x 6",
      "part_cat_id": "11",
      "part_material": "Plastic",
      "colorName": "Reddish Brown"
    },
    {
      "inventory_id": "42622",
      "part_num": "24866",
      "color_id": "2",
      "quantity": "6",
      "is_spare": "f",
      "img_url": "https://cdn.rebrickable.com/media/parts/elements/6135287.jpg",
      "name": "Plant, Flower, Plate Round 1 x 1 with 5 Petals",
      "part_cat_id": "28",
      "part_material": "Plastic",
      "colorName": "Green"
    },
    {
      "inventory_id": "42622",
      "part_num": "24866",
      "color_id": "10",
      "quantity": "12",
      "is_spare": "f",
      "img_url": "https://cdn.rebrickable.com/media/parts/elements/6206150.jpg",
      "name": "Plant, Flower, Plate Round 1 x 1 with 5 Petals",
      "part_cat_id": "28",
      "part_material": "Plastic",
      "colorName": "Bright Green"
    },
    {
      "inventory_id": "42622",
      "part_num": "25893",
      "color_id": "47",
      "quantity": "1",
      "is_spare": "f",
      "img_url": "https://cdn.rebrickable.com/media/parts/elements/6153264.jpg",
      "name": "Plate Round 1 x 1 with Hollow Stud and Bar on Underside",
      "part_cat_id": "9",
      "part_material": "Plastic",
      "colorName": "Trans-Clear"
    },
    {
      "inventory_id": "42622",
      "part_num": "2736",
      "color_id": "71",
      "quantity": "1",
      "is_spare": "f",
      "img_url": "https://cdn.rebrickable.com/media/parts/elements/4211375.jpg",
      "name": "Technic Axle Towball",
      "part_cat_id": "53",
      "part_material": "Plastic",
      "colorName": "Light Bluish Gray"
    },
    {
      "inventory_id": "42622",
      "part_num": "2780",
      "color_id": "0",
      "quantity": "1",
      "is_spare": "f",
      "img_url": "https://cdn.rebrickable.com/media/parts/elements/4121715.jpg",
      "name": "Technic Pin with Friction Ridges Lengthwise and Center Slots",
      "part_cat_id": "53",
      "part_material": "Plastic",
      "colorName": "Black"
    },
    {
      "inventory_id": "42622",
      "part_num": "2921",
      "color_id": "84",
      "quantity": "1",
      "is_spare": "f",
      "img_url": "https://cdn.rebrickable.com/media/parts/elements/6102959.jpg",
      "name": "Brick Special 1 x 1 with Handle",
      "part_cat_id": "5",
      "part_material": "Plastic",
      "colorName": "Medium Nougat"
    },
    {
      "inventory_id": "42622",
      "part_num": "3001",
      "color_id": "19",
      "quantity": "2",
      "is_spare": "f",
      "img_url": "https://cdn.rebrickable.com/media/parts/elements/4114319.jpg",
      "name": "Brick 2 x 4",
      "part_cat_id": "11",
      "part_material": "Plastic",
      "colorName": "Tan"
    },
    {
      "inventory_id": "42622",
      "part_num": "3001",
      "color_id": "288",
      "quantity": "8",
      "is_spare": "f",
      "img_url": "https://cdn.rebrickable.com/media/parts/elements/4260493.jpg",
      "name": "Brick 2 x 4",
      "part_cat_id": "11",
      "part_material": "Plastic",
      "colorName": "Dark Green"
    },
    {
      "inventory_id": "42622",
      "part_num": "3001",
      "color_id": "70",
      "quantity": "1",
      "is_spare": "f",
      "img_url": "https://cdn.rebrickable.com/media/parts/elements/4211201.jpg",
      "name": "Brick 2 x 4",
      "part_cat_id": "11",
      "part_material": "Plastic",
      "colorName": "Reddish Brown"
    },
    {
      "inventory_id": "42622",
      "part_num": "3002",
      "color_id": "70",
      "quantity": "1",
      "is_spare": "f",
      "img_url": "https://cdn.rebrickable.com/media/parts/elements/4216668.jpg",
      "name": "Brick 2 x 3",
      "part_cat_id": "11",
      "part_material": "Plastic",
      "colorName": "Reddish Brown"
    },
    {
      "inventory_id": "42622",
      "part_num": "3003",
      "color_id": "70",
      "quantity": "4",
      "is_spare": "f",
      "img_url": "https://cdn.rebrickable.com/media/parts/elements/4211210.jpg",
      "name": "Brick 2 x 2",
      "part_cat_id": "11",
      "part_material": "Plastic",
      "colorName": "Reddish Brown"
    },
    {
      "inventory_id": "42622",
      "part_num": "3003",
      "color_id": "484",
      "quantity": "11",
      "is_spare": "f",
      "img_url": "https://cdn.rebrickable.com/media/parts/elements/4164440.jpg",
      "name": "Brick 2 x 2",
      "part_cat_id": "11",
      "part_material": "Plastic",
      "colorName": "Dark Orange"
    },
    {
      "inventory_id": "42622",
      "part_num": "3003",
      "color_id": "288",
      "quantity": "1",
      "is_spare": "f",
      "img_url": "https://cdn.rebrickable.com/media/parts/elements/4266895.jpg",
      "name": "Brick 2 x 2",
      "part_cat_id": "11",
      "part_material": "Plastic",
      "colorName": "Dark Green"
    },
    {
      "inventory_id": "42622",
      "part_num": "3003",
      "color_id": "72",
      "quantity": "8",
      "is_spare": "f",
      "img_url": "https://cdn.rebrickable.com/media/parts/elements/4211060.jpg",
      "name": "Brick 2 x 2",
      "part_cat_id": "11",
      "part_material": "Plastic",
      "colorName": "Dark Bluish Gray"
    },
    {
      "inventory_id": "42622",
      "part_num": "3003",
      "color_id": "19",
      "quantity": "20",
      "is_spare": "f",
      "img_url": "https://cdn.rebrickable.com/media/parts/elements/4114306.jpg",
      "name": "Brick 2 x 2",
      "part_cat_id": "11",
      "part_material": "Plastic",
      "colorName": "Tan"
    },
    {
      "inventory_id": "42622",
      "part_num": "3004",
      "color_id": "19",
      "quantity": "9",
      "is_spare": "f",
      "img_url": "https://cdn.rebrickable.com/media/parts/elements/4109995.jpg",
      "name": "Brick 1 x 2",
      "part_cat_id": "11",
      "part_material": "Plastic",
      "colorName": "Tan"
    },
    {
      "inventory_id": "42622",
      "part_num": "3004",
      "color_id": "84",
      "quantity": "2",
      "is_spare": "f",
      "img_url": "https://cdn.rebrickable.com/media/parts/elements/4569382.jpg",
      "name": "Brick 1 x 2",
      "part_cat_id": "11",
      "part_material": "Plastic",
      "colorName": "Medium Nougat"
    },
    {
      "inventory_id": "42622",
      "part_num": "3004pr0014",
      "color_id": "84",
      "quantity": "2",
      "is_spare": "f",
      "img_url": "https://cdn.rebrickable.com/media/parts/elements/6097024.jpg",
      "name": "Brick 1 x 2 with Reddish Brown and Dark Brown Lines Print",
      "part_cat_id": "11",
      "part_material": "Plastic",
      "colorName": "Medium Nougat"
    },
    {
      "inventory_id": "42622",
      "part_num": "3004pr0020",
      "color_id": "72",
      "quantity": "1",
      "is_spare": "f",
      "img_url": "https://cdn.rebrickable.com/media/parts/elements/6216862.jpg",
      "name": "Brick 1 x 2 with Minecraft Pixelated Lit Forge Print",
      "part_cat_id": "11",
      "part_material": "Plastic",
      "colorName": "Dark Bluish Gray"
    },
    {
      "inventory_id": "42622",
      "part_num": "3004pr0021",
      "color_id": "72",
      "quantity": "1",
      "is_spare": "f",
      "img_url": "https://cdn.rebrickable.com/media/parts/elements/6216860.jpg",
      "name": "Brick 1 x 2 with Pixelated Forge Print",
      "part_cat_id": "11",
      "part_material": "Plastic",
      "colorName": "Dark Bluish Gray"
    },
    {
      "inventory_id": "42622",
      "part_num": "3005",
      "color_id": "308",
      "quantity": "1",
      "is_spare": "f",
      "img_url": "https://cdn.rebrickable.com/media/parts/elements/6226437.jpg",
      "name": "Brick 1 x 1",
      "part_cat_id": "11",
      "part_material": "Plastic",
      "colorName": "Dark Brown"
    },
    {
      "inventory_id": "42622",
      "part_num": "3005",
      "color_id": "1",
      "quantity": "1",
      "is_spare": "f",
      "img_url": "https://cdn.rebrickable.com/media/parts/elements/300523.jpg",
      "name": "Brick 1 x 1",
      "part_cat_id": "11",
      "part_material": "Plastic",
      "colorName": "Blue"
    },
    {
      "inventory_id": "42622",
      "part_num": "3005",
      "color_id": "19",
      "quantity": "14",
      "is_spare": "f",
      "img_url": "https://cdn.rebrickable.com/media/parts/elements/4113915.jpg",
      "name": "Brick 1 x 1",
      "part_cat_id": "11",
      "part_material": "Plastic",
      "colorName": "Tan"
    },
    {
      "inventory_id": "42622",
      "part_num": "3005",
      "color_id": "27",
      "quantity": "1",
      "is_spare": "f",
      "img_url": "https://cdn.rebrickable.com/media/parts/elements/4220634.jpg",
      "name": "Brick 1 x 1",
      "part_cat_id": "11",
      "part_material": "Plastic",
      "colorName": "Lime"
    },
    {
      "inventory_id": "42622",
      "part_num": "3005",
      "color_id": "84",
      "quantity": "1",
      "is_spare": "f",
      "img_url": "https://cdn.rebrickable.com/media/parts/elements/4569624.jpg",
      "name": "Brick 1 x 1",
      "part_cat_id": "11",
      "part_material": "Plastic",
      "colorName": "Medium Nougat"
    },
    {
      "inventory_id": "42622",
      "part_num": "3009",
      "color_id": "70",
      "quantity": "2",
      "is_spare": "f",
      "img_url": "https://cdn.rebrickable.com/media/parts/elements/4211193.jpg",
      "name": "Brick 1 x 6",
      "part_cat_id": "11",
      "part_material": "Plastic",
      "colorName": "Reddish Brown"
    },
    {
      "inventory_id": "42622",
      "part_num": "3009",
      "color_id": "19",
      "quantity": "6",
      "is_spare": "f",
      "img_url": "https://cdn.rebrickable.com/media/parts/elements/4112982.jpg",
      "name": "Brick 1 x 6",
      "part_cat_id": "11",
      "part_material": "Plastic",
      "colorName": "Tan"
    },
    {
      "inventory_id": "42622",
      "part_num": "3010",
      "color_id": "19",
      "quantity": "4",
      "is_spare": "f",
      "img_url": "https://cdn.rebrickable.com/media/parts/elements/4113916.jpg",
      "name": "Brick 1 x 4",
      "part_cat_id": "11",
      "part_material": "Plastic",
      "colorName": "Tan"
    },
    {
      "inventory_id": "42622",
      "part_num": "3020",
      "color_id": "322",
      "quantity": "2",
      "is_spare": "f",
      "img_url": "https://cdn.rebrickable.com/media/parts/elements/4655256.jpg",
      "name": "Plate 2 x 4",
      "part_cat_id": "14",
      "part_material": "Plastic",
      "colorName": "Medium Azure"
    },
    {
      "inventory_id": "42622",
      "part_num": "3020",
      "color_id": "19",
      "quantity": "8",
      "is_spare": "f",
      "img_url": "https://cdn.rebrickable.com/media/parts/elements/4114309.jpg",
      "name": "Plate 2 x 4",
      "part_cat_id": "14",
      "part_material": "Plastic",
      "colorName": "Tan"
    },
    {
      "inventory_id": "42622",
      "part_num": "3020",
      "color_id": "70",
      "quantity": "12",
      "is_spare": "f",
      "img_url": "https://cdn.rebrickable.com/media/parts/elements/4211186.jpg",
      "name": "Plate 2 x 4",
      "part_cat_id": "14",
      "part_material": "Plastic",
      "colorName": "Reddish Brown"
    },
    {
      "inventory_id": "42622",
      "part_num": "3020",
      "color_id": "28",
      "quantity": "4",
      "is_spare": "f",
      "img_url": "https://cdn.rebrickable.com/media/parts/elements/4267874.jpg",
      "name": "Plate 2 x 4",
      "part_cat_id": "14",
      "part_material": "Plastic",
      "colorName": "Dark Tan"
    },
    {
      "inventory_id": "42622",
      "part_num": "3020",
      "color_id": "27",
      "quantity": "1",
      "is_spare": "f",
      "img_url": "https://cdn.rebrickable.com/media/parts/elements/4164023.jpg",
      "name": "Plate 2 x 4",
      "part_cat_id": "14",
      "part_material": "Plastic",
      "colorName": "Lime"
    },
    {
      "inventory_id": "42622",
      "part_num": "3021",
      "color_id": "70",
      "quantity": "6",
      "is_spare": "f",
      "img_url": "https://cdn.rebrickable.com/media/parts/elements/4211189.jpg",
      "name": "Plate 2 x 3",
      "part_cat_id": "14",
      "part_material": "Plastic",
      "colorName": "Reddish Brown"
    },
    {
      "inventory_id": "42622",
      "part_num": "3021",
      "color_id": "29",
      "quantity": "2",
      "is_spare": "f",
      "img_url": "https://cdn.rebrickable.com/media/parts/elements/6102999.jpg",
      "name": "Plate 2 x 3",
      "part_cat_id": "14",
      "part_material": "Plastic",
      "colorName": "Bright Pink"
    },
    {
      "inventory_id": "42622",
      "part_num": "3022",
      "color_id": "29",
      "quantity": "1",
      "is_spare": "f",
      "img_url": "https://cdn.rebrickable.com/media/parts/elements/6096589.jpg",
      "name": "Plate 2 x 2",
      "part_cat_id": "14",
      "part_material": "Plastic",
      "colorName": "Bright Pink"
    },
    {
      "inventory_id": "42622",
      "part_num": "3022",
      "color_id": "84",
      "quantity": "1",
      "is_spare": "f",
      "img_url": "https://cdn.rebrickable.com/media/parts/elements/6056383.jpg",
      "name": "Plate 2 x 2",
      "part_cat_id": "14",
      "part_material": "Plastic",
      "colorName": "Medium Nougat"
    },
    {
      "inventory_id": "42622",
      "part_num": "3022",
      "color_id": "14",
      "quantity": "2",
      "is_spare": "f",
      "img_url": "https://cdn.rebrickable.com/media/parts/elements/302224.jpg",
      "name": "Plate 2 x 2",
      "part_cat_id": "14",
      "part_material": "Plastic",
      "colorName": "Yellow"
    },
    {
      "inventory_id": "42622",
      "part_num": "3022",
      "color_id": "70",
      "quantity": "8",
      "is_spare": "f",
      "img_url": "https://cdn.rebrickable.com/media/parts/elements/4216695.jpg",
      "name": "Plate 2 x 2",
      "part_cat_id": "14",
      "part_material": "Plastic",
      "colorName": "Reddish Brown"
    },
    {
      "inventory_id": "42622",
      "part_num": "3022",
      "color_id": "15",
      "quantity": "5",
      "is_spare": "f",
      "img_url": "https://cdn.rebrickable.com/media/parts/elements/302201.jpg",
      "name": "Plate 2 x 2",
      "part_cat_id": "14",
      "part_material": "Plastic",
      "colorName": "White"
    },
    {
      "inventory_id": "42622",
      "part_num": "3022",
      "color_id": "4",
      "quantity": "1",
      "is_spare": "f",
      "img_url": "https://cdn.rebrickable.com/media/parts/elements/302221.jpg",
      "name": "Plate 2 x 2",
      "part_cat_id": "14",
      "part_material": "Plastic",
      "colorName": "Red"
    },
    {
      "inventory_id": "42622",
      "part_num": "3022",
      "color_id": "379",
      "quantity": "4",
      "is_spare": "f",
      "img_url": "https://cdn.rebrickable.com/media/parts/elements/4153607.jpg",
      "name": "Plate 2 x 2",
      "part_cat_id": "14",
      "part_material": "Plastic",
      "colorName": "Sand Blue"
    },
    {
      "inventory_id": "42622",
      "part_num": "3022",
      "color_id": "19",
      "quantity": "13",
      "is_spare": "f",
      "img_url": "https://cdn.rebrickable.com/media/parts/elements/4114084.jpg",
      "name": "Plate 2 x 2",
      "part_cat_id": "14",
      "part_material": "Plastic",
      "colorName": "Tan"
    },
    {
      "inventory_id": "42622",
      "part_num": "3022",
      "color_id": "484",
      "quantity": "1",
      "is_spare": "f",
      "img_url": "https://cdn.rebrickable.com/media/parts/elements/4165522.jpg",
      "name": "Plate 2 x 2",
      "part_cat_id": "14",
      "part_material": "Plastic",
      "colorName": "Dark Orange"
    },
    {
      "inventory_id": "42622",
      "part_num": "3023",
      "color_id": "70",
      "quantity": "10",
      "is_spare": "f",
      "img_url": "https://cdn.rebrickable.com/media/parts/elements/4211150.jpg",
      "name": "Plate 1 x 2",
      "part_cat_id": "14",
      "part_material": "Plastic",
      "colorName": "Reddish Brown"
    },
    {
      "inventory_id": "42622",
      "part_num": "3023",
      "color_id": "19",
      "quantity": "4",
      "is_spare": "f",
      "img_url": "https://cdn.rebrickable.com/media/parts/elements/4113917.jpg",
      "name": "Plate 1 x 2",
      "part_cat_id": "14",
      "part_material": "Plastic",
      "colorName": "Tan"
    },
    {
      "inventory_id": "42622",
      "part_num": "3023",
      "color_id": "71",
      "quantity": "16",
      "is_spare": "f",
      "img_url": "https://cdn.rebrickable.com/media/parts/elements/4211398.jpg",
      "name": "Plate 1 x 2",
      "part_cat_id": "14",
      "part_material": "Plastic",
      "colorName": "Light Bluish Gray"
    },
    {
      "inventory_id": "42622",
      "part_num": "3023",
      "color_id": "33",
      "quantity": "6",
      "is_spare": "f",
      "img_url": "https://cdn.rebrickable.com/media/parts/elements/4260426.jpg",
      "name": "Plate 1 x 2",
      "part_cat_id": "14",
      "part_material": "Plastic",
      "colorName": "Trans-Dark Blue"
    },
    {
      "inventory_id": "42622",
      "part_num": "3024",
      "color_id": "0",
      "quantity": "1",
      "is_spare": "f",
      "img_url": "https://cdn.rebrickable.com/media/parts/elements/302426.jpg",
      "name": "Plate 1 x 1",
      "part_cat_id": "14",
      "part_material": "Plastic",
      "colorName": "Black"
    },
    {
      "inventory_id": "42622",
      "part_num": "3024",
      "color_id": "28",
      "quantity": "3",
      "is_spare": "f",
      "img_url": "https://cdn.rebrickable.com/media/parts/elements/4549436.jpg",
      "name": "Plate 1 x 1",
      "part_cat_id": "14",
      "part_material": "Plastic",
      "colorName": "Dark Tan"
    },
    {
      "inventory_id": "42622",
      "part_num": "3024",
      "color_id": "19",
      "quantity": "1",
      "is_spare": "f",
      "img_url": "https://cdn.rebrickable.com/media/parts/elements/4159553.jpg",
      "name": "Plate 1 x 1",
      "part_cat_id": "14",
      "part_material": "Plastic",
      "colorName": "Tan"
    },
    {
      "inventory_id": "42622",
      "part_num": "3024",
      "color_id": "4",
      "quantity": "2",
      "is_spare": "f",
      "img_url": "https://cdn.rebrickable.com/media/parts/elements/302421.jpg",
      "name": "Plate 1 x 1",
      "part_cat_id": "14",
      "part_material": "Plastic",
      "colorName": "Red"
    },
    {
      "inventory_id": "42622",
      "part_num": "3024",
      "color_id": "182",
      "quantity": "1",
      "is_spare": "f",
      "img_url": "https://cdn.rebrickable.com/media/parts/elements/4542673.jpg",
      "name": "Plate 1 x 1",
      "part_cat_id": "14",
      "part_material": "Plastic",
      "colorName": "Trans-Orange"
    },
    {
      "inventory_id": "42622",
      "part_num": "3024",
      "color_id": "1",
      "quantity": "8",
      "is_spare": "f",
      "img_url": "https://cdn.rebrickable.com/media/parts/elements/302423.jpg",
      "name": "Plate 1 x 1",
      "part_cat_id": "14",
      "part_material": "Plastic",
      "colorName": "Blue"
    },
    {
      "inventory_id": "42622",
      "part_num": "3024",
      "color_id": "297",
      "quantity": "2",
      "is_spare": "f",
      "img_url": "https://cdn.rebrickable.com/media/parts/elements/6069887.jpg",
      "name": "Plate 1 x 1",
      "part_cat_id": "14",
      "part_material": "Plastic",
      "colorName": "Pearl Gold"
    },
    {
      "inventory_id": "42622",
      "part_num": "3024",
      "color_id": "46",
      "quantity": "1",
      "is_spare": "f",
      "img_url": "https://cdn.rebrickable.com/media/parts/elements/3000844.jpg",
      "name": "Plate 1 x 1",
      "part_cat_id": "14",
      "part_material": "Plastic",
      "colorName": "Trans-Yellow"
    },
    {
      "inventory_id": "42622",
      "part_num": "3024",
      "color_id": "484",
      "quantity": "6",
      "is_spare": "f",
      "img_url": "https://cdn.rebrickable.com/media/parts/elements/6186012.jpg",
      "name": "Plate 1 x 1",
      "part_cat_id": "14",
      "part_material": "Plastic",
      "colorName": "Dark Orange"
    },
    {
      "inventory_id": "42622",
      "part_num": "3024",
      "color_id": "15",
      "quantity": "3",
      "is_spare": "f",
      "img_url": "https://cdn.rebrickable.com/media/parts/elements/302401.jpg",
      "name": "Plate 1 x 1",
      "part_cat_id": "14",
      "part_material": "Plastic",
      "colorName": "White"
    },
    {
      "inventory_id": "42622",
      "part_num": "3024",
      "color_id": "2",
      "quantity": "2",
      "is_spare": "f",
      "img_url": "https://cdn.rebrickable.com/media/parts/elements/302428.jpg",
      "name": "Plate 1 x 1",
      "part_cat_id": "14",
      "part_material": "Plastic",
      "colorName": "Green"
    },
    {
      "inventory_id": "42622",
      "part_num": "3024",
      "color_id": "14",
      "quantity": "8",
      "is_spare": "f",
      "img_url": "https://cdn.rebrickable.com/media/parts/elements/302424.jpg",
      "name": "Plate 1 x 1",
      "part_cat_id": "14",
      "part_material": "Plastic",
      "colorName": "Yellow"
    },
    {
      "inventory_id": "42622",
      "part_num": "3031",
      "color_id": "2",
      "quantity": "2",
      "is_spare": "f",
      "img_url": "https://cdn.rebrickable.com/media/parts/elements/4113158.jpg",
      "name": "Plate 4 x 4",
      "part_cat_id": "14",
      "part_material": "Plastic",
      "colorName": "Green"
    },
    {
      "inventory_id": "42622",
      "part_num": "3032",
      "color_id": "19",
      "quantity": "3",
      "is_spare": "f",
      "img_url": "https://cdn.rebrickable.com/media/parts/elements/4114001.jpg",
      "name": "Plate 4 x 6",
      "part_cat_id": "14",
      "part_material": "Plastic",
      "colorName": "Tan"
    },
    {
      "inventory_id": "42622",
      "part_num": "3032",
      "color_id": "0",
      "quantity": "1",
      "is_spare": "f",
      "img_url": "https://cdn.rebrickable.com/media/parts/elements/303226.jpg",
      "name": "Plate 4 x 6",
      "part_cat_id": "14",
      "part_material": "Plastic",
      "colorName": "Black"
    },
    {
      "inventory_id": "42622",
      "part_num": "3033",
      "color_id": "27",
      "quantity": "1",
      "is_spare": "f",
      "img_url": "https://cdn.rebrickable.com/media/parts/elements/4172875.jpg",
      "name": "Plate 6 x 10",
      "part_cat_id": "14",
      "part_material": "Plastic",
      "colorName": "Lime"
    },
    {
      "inventory_id": "42622",
      "part_num": "3033",
      "color_id": "484",
      "quantity": "2",
      "is_spare": "f",
      "img_url": "https://cdn.rebrickable.com/media/parts/elements/6263971.jpg",
      "name": "Plate 6 x 10",
      "part_cat_id": "14",
      "part_material": "Plastic",
      "colorName": "Dark Orange"
    },
    {
      "inventory_id": "42622",
      "part_num": "3034",
      "color_id": "72",
      "quantity": "1",
      "is_spare": "f",
      "img_url": "https://cdn.rebrickable.com/media/parts/elements/4210997.jpg",
      "name": "Plate 2 x 8",
      "part_cat_id": "14",
      "part_material": "Plastic",
      "colorName": "Dark Bluish Gray"
    },
    {
      "inventory_id": "42622",
      "part_num": "3034",
      "color_id": "326",
      "quantity": "1",
      "is_spare": "f",
      "img_url": "https://cdn.rebrickable.com/media/parts/elements/6073988.jpg",
      "name": "Plate 2 x 8",
      "part_cat_id": "14",
      "part_material": "Plastic",
      "colorName": "Olive Green"
    },
    {
      "inventory_id": "42622",
      "part_num": "3035",
      "color_id": "1",
      "quantity": "1",
      "is_spare": "f",
      "img_url": "https://cdn.rebrickable.com/media/parts/elements/303523.jpg",
      "name": "Plate 4 x 8",
      "part_cat_id": "14",
      "part_material": "Plastic",
      "colorName": "Blue"
    },
    {
      "inventory_id": "42622",
      "part_num": "30350cpr0013",
      "color_id": "0",
      "quantity": "1",
      "is_spare": "f",
      "img_url": "https://cdn.rebrickable.com/media/parts/elements/6290248.jpg",
      "name": "Tile Special 2 x 3 with 2 Clips with Gray, White and Turquoise Squares (Face) Print",
      "part_cat_id": "15",
      "part_material": "Plastic",
      "colorName": "Black"
    },
    {
      "inventory_id": "42622",
      "part_num": "3036",
      "color_id": "19",
      "quantity": "5",
      "is_spare": "f",
      "img_url": "https://cdn.rebrickable.com/media/parts/elements/4114056.jpg",
      "name": "Plate 6 x 8",
      "part_cat_id": "14",
      "part_material": "Plastic",
      "colorName": "Tan"
    },
    {
      "inventory_id": "42622",
      "part_num": "30374",
      "color_id": "14",
      "quantity": "1",
      "is_spare": "f",
      "img_url": "https://cdn.rebrickable.com/media/parts/elements/4193511.jpg",
      "name": "Bar 4L (Lightsaber Blade / Wand)",
      "part_cat_id": "32",
      "part_material": "Plastic",
      "colorName": "Yellow"
    },
    {
      "inventory_id": "42622",
      "part_num": "3068b",
      "color_id": "27",
      "quantity": "3",
      "is_spare": "f",
      "img_url": "https://cdn.rebrickable.com/media/parts/elements/4518611.jpg",
      "name": "Tile 2 x 2 with Groove",
      "part_cat_id": "19",
      "part_material": "Plastic",
      "colorName": "Lime"
    },
    {
      "inventory_id": "42622",
      "part_num": "3068b",
      "color_id": "15",
      "quantity": "1",
      "is_spare": "f",
      "img_url": "https://cdn.rebrickable.com/media/parts/elements/306801.jpg",
      "name": "Tile 2 x 2 with Groove",
      "part_cat_id": "19",
      "part_material": "Plastic",
      "colorName": "White"
    },
    {
      "inventory_id": "42622",
      "part_num": "3068b",
      "color_id": "84",
      "quantity": "1",
      "is_spare": "f",
      "img_url": "https://cdn.rebrickable.com/media/parts/elements/6102990.jpg",
      "name": "Tile 2 x 2 with Groove",
      "part_cat_id": "19",
      "part_material": "Plastic",
      "colorName": "Medium Nougat"
    },
    {
      "inventory_id": "42622",
      "part_num": "3068bpr0236",
      "color_id": "84",
      "quantity": "1",
      "is_spare": "f",
      "img_url": "https://cdn.rebrickable.com/media/parts/elements/6097003.jpg",
      "name": "Tile 2 x 2 with Dark Brown Minecraft Grid Print (Crafting Table)",
      "part_cat_id": "19",
      "part_material": "Plastic",
      "colorName": "Medium Nougat"
    },
    {
      "inventory_id": "42622",
      "part_num": "3068bpr0417",
      "color_id": "15",
      "quantity": "2",
      "is_spare": "f",
      "img_url": "https://cdn.rebrickable.com/media/parts/elements/6290444.jpg",
      "name": "Tile 2 x 2 with Groove and Pixelated Blue and Orange Squares Print",
      "part_cat_id": "19",
      "part_material": "Plastic",
      "colorName": "White"
    },
    {
      "inventory_id": "42622",
      "part_num": "3069b",
      "color_id": "0",
      "quantity": "2",
      "is_spare": "f",
      "img_url": "https://cdn.rebrickable.com/media/parts/elements/306926.jpg",
      "name": "Tile 1 x 2 with Groove",
      "part_cat_id": "19",
      "part_material": "Plastic",
      "colorName": "Black"
    },
    {
      "inventory_id": "42622",
      "part_num": "3069b",
      "color_id": "191",
      "quantity": "1",
      "is_spare": "f",
      "img_url": "https://cdn.rebrickable.com/media/parts/elements/4622062.jpg",
      "name": "Tile 1 x 2 with Groove",
      "part_cat_id": "19",
      "part_material": "Plastic",
      "colorName": "Bright Light Orange"
    },
    {
      "inventory_id": "42622",
      "part_num": "3069b",
      "color_id": "379",
      "quantity": "4",
      "is_spare": "f",
      "img_url": "https://cdn.rebrickable.com/media/parts/elements/4170251.jpg",
      "name": "Tile 1 x 2 with Groove",
      "part_cat_id": "19",
      "part_material": "Plastic",
      "colorName": "Sand Blue"
    },
    {
      "inventory_id": "42622",
      "part_num": "3069b",
      "color_id": "484",
      "quantity": "3",
      "is_spare": "f",
      "img_url": "https://cdn.rebrickable.com/media/parts/elements/4614158.jpg",
      "name": "Tile 1 x 2 with Groove",
      "part_cat_id": "19",
      "part_material": "Plastic",
      "colorName": "Dark Orange"
    },
    {
      "inventory_id": "42622",
      "part_num": "3070b",
      "color_id": "84",
      "quantity": "1",
      "is_spare": "f",
      "img_url": "https://cdn.rebrickable.com/media/parts/elements/6177146.jpg",
      "name": "Tile 1 x 1 with Groove",
      "part_cat_id": "19",
      "part_material": "Plastic",
      "colorName": "Medium Nougat"
    },
    {
      "inventory_id": "42622",
      "part_num": "3070b",
      "color_id": "0",
      "quantity": "2",
      "is_spare": "f",
      "img_url": "https://cdn.rebrickable.com/media/parts/elements/307026.jpg",
      "name": "Tile 1 x 1 with Groove",
      "part_cat_id": "19",
      "part_material": "Plastic",
      "colorName": "Black"
    },
    {
      "inventory_id": "42622",
      "part_num": "32013",
      "color_id": "308",
      "quantity": "1",
      "is_spare": "f",
      "img_url": "https://cdn.rebrickable.com/media/parts/elements/6167932.jpg",
      "name": "Technic Axle and Pin Connector Angled #1",
      "part_cat_id": "12",
      "part_material": "Plastic",
      "colorName": "Dark Brown"
    },
    {
      "inventory_id": "42622",
      "part_num": "32124",
      "color_id": "0",
      "quantity": "1",
      "is_spare": "f",
      "img_url": "https://cdn.rebrickable.com/media/parts/elements/4114689.jpg",
      "name": "Technic Plate 1 x 5 with Smooth Ends, 4 Studs and Centre Axle Hole",
      "part_cat_id": "26",
      "part_material": "Plastic",
      "colorName": "Black"
    },
    {
      "inventory_id": "42622",
      "part_num": "3245c",
      "color_id": "19",
      "quantity": "2",
      "is_spare": "f",
      "img_url": "https://cdn.rebrickable.com/media/parts/elements/4159279.jpg",
      "name": "Brick 1 x 2 x 2 with Inside Stud Holder",
      "part_cat_id": "11",
      "part_material": "Plastic",
      "colorName": "Tan"
    },
    {
      "inventory_id": "42622",
      "part_num": "33172",
      "color_id": "25",
      "quantity": "2",
      "is_spare": "f",
      "img_url": "https://cdn.rebrickable.com/media/parts/elements/4119478.jpg",
      "name": "Plant, Carrot",
      "part_cat_id": "28",
      "part_material": "Plastic",
      "colorName": "Orange"
    },
    {
      "inventory_id": "42622",
      "part_num": "33183",
      "color_id": "191",
      "quantity": "2",
      "is_spare": "f",
      "img_url": "https://cdn.rebrickable.com/media/parts/elements/6096682.jpg",
      "name": "Plant, Carrot Top",
      "part_cat_id": "28",
      "part_material": "Plastic",
      "colorName": "Bright Light Orange"
    },
    {
      "inventory_id": "42622",
      "part_num": "33183",
      "color_id": "10",
      "quantity": "4",
      "is_spare": "f",
      "img_url": "https://cdn.rebrickable.com/media/parts/elements/4119479.jpg",
      "name": "Plant, Carrot Top",
      "part_cat_id": "28",
      "part_material": "Plastic",
      "colorName": "Bright Green"
    },
    {
      "inventory_id": "42622",
      "part_num": "34103",
      "color_id": "484",
      "quantity": "5",
      "is_spare": "f",
      "img_url": "https://cdn.rebrickable.com/media/parts/elements/6290986.jpg",
      "name": "Plate Special 1 x 3 with 2 Studs with Groove and Inside Stud Holder (Jumper)",
      "part_cat_id": "9",
      "part_material": "Plastic",
      "colorName": "Dark Orange"
    },
    {
      "inventory_id": "42622",
      "part_num": "3460",
      "color_id": "19",
      "quantity": "6",
      "is_spare": "f",
      "img_url": "https://cdn.rebrickable.com/media/parts/elements/4114324.jpg",
      "name": "Plate 1 x 8",
      "part_cat_id": "14",
      "part_material": "Plastic",
      "colorName": "Tan"
    },
    {
      "inventory_id": "42622",
      "part_num": "35459",
      "color_id": "71",
      "quantity": "2",
      "is_spare": "f",
      "img_url": "https://cdn.rebrickable.com/media/parts/elements/6251044.jpg",
      "name": "Tile Special 1 x 3 Inverted with Center Hole",
      "part_cat_id": "15",
      "part_material": "Plastic",
      "colorName": "Light Bluish Gray"
    },
    {
      "inventory_id": "42622",
      "part_num": "3622",
      "color_id": "70",
      "quantity": "2",
      "is_spare": "f",
      "img_url": "https://cdn.rebrickable.com/media/parts/elements/4211220.jpg",
      "name": "Brick 1 x 3",
      "part_cat_id": "11",
      "part_material": "Plastic",
      "colorName": "Reddish Brown"
    },
    {
      "inventory_id": "42622",
      "part_num": "3622pr0055",
      "color_id": "70",
      "quantity": "1",
      "is_spare": "f",
      "img_url": "https://cdn.rebrickable.com/media/parts/elements/6290437.jpg",
      "name": "Brick 1 x 3 with Black Line and White and Green Squares (Eyes) Print",
      "part_cat_id": "11",
      "part_material": "Plastic",
      "colorName": "Reddish Brown"
    },
    {
      "inventory_id": "42622",
      "part_num": "3623",
      "color_id": "19",
      "quantity": "4",
      "is_spare": "f",
      "img_url": "https://cdn.rebrickable.com/media/parts/elements/4121921.jpg",
      "name": "Plate 1 x 3",
      "part_cat_id": "14",
      "part_material": "Plastic",
      "colorName": "Tan"
    },
    {
      "inventory_id": "42622",
      "part_num": "3623",
      "color_id": "15",
      "quantity": "1",
      "is_spare": "f",
      "img_url": "https://cdn.rebrickable.com/media/parts/elements/362301.jpg",
      "name": "Plate 1 x 3",
      "part_cat_id": "14",
      "part_material": "Plastic",
      "colorName": "White"
    },
    {
      "inventory_id": "42622",
      "part_num": "3666",
      "color_id": "72",
      "quantity": "1",
      "is_spare": "f",
      "img_url": "https://cdn.rebrickable.com/media/parts/elements/4211056.jpg",
      "name": "Plate 1 x 6",
      "part_cat_id": "14",
      "part_material": "Plastic",
      "colorName": "Dark Bluish Gray"
    },
    {
      "inventory_id": "42622",
      "part_num": "3666",
      "color_id": "19",
      "quantity": "5",
      "is_spare": "f",
      "img_url": "https://cdn.rebrickable.com/media/parts/elements/4124067.jpg",
      "name": "Plate 1 x 6",
      "part_cat_id": "14",
      "part_material": "Plastic",
      "colorName": "Tan"
    },
    {
      "inventory_id": "42622",
      "part_num": "3710",
      "color_id": "70",
      "quantity": "1",
      "is_spare": "f",
      "img_url": "https://cdn.rebrickable.com/media/parts/elements/4211190.jpg",
      "name": "Plate 1 x 4",
      "part_cat_id": "14",
      "part_material": "Plastic",
      "colorName": "Reddish Brown"
    },
    {
      "inventory_id": "42622",
      "part_num": "3710",
      "color_id": "484",
      "quantity": "4",
      "is_spare": "f",
      "img_url": "https://cdn.rebrickable.com/media/parts/elements/4164448.jpg",
      "name": "Plate 1 x 4",
      "part_cat_id": "14",
      "part_material": "Plastic",
      "colorName": "Dark Orange"
    },
    {
      "inventory_id": "42622",
      "part_num": "3710",
      "color_id": "19",
      "quantity": "4",
      "is_spare": "f",
      "img_url": "https://cdn.rebrickable.com/media/parts/elements/4113233.jpg",
      "name": "Plate 1 x 4",
      "part_cat_id": "14",
      "part_material": "Plastic",
      "colorName": "Tan"
    },
    {
      "inventory_id": "42622",
      "part_num": "3795",
      "color_id": "28",
      "quantity": "4",
      "is_spare": "f",
      "img_url": "https://cdn.rebrickable.com/media/parts/elements/4550329.jpg",
      "name": "Plate 2 x 6",
      "part_cat_id": "14",
      "part_material": "Plastic",
      "colorName": "Dark Tan"
    },
    {
      "inventory_id": "42622",
      "part_num": "3795",
      "color_id": "484",
      "quantity": "1",
      "is_spare": "f",
      "img_url": "https://cdn.rebrickable.com/media/parts/elements/6219673.jpg",
      "name": "Plate 2 x 6",
      "part_cat_id": "14",
      "part_material": "Plastic",
      "colorName": "Dark Orange"
    },
    {
      "inventory_id": "42622",
      "part_num": "3795",
      "color_id": "19",
      "quantity": "4",
      "is_spare": "f",
      "img_url": "https://cdn.rebrickable.com/media/parts/elements/4113993.jpg",
      "name": "Plate 2 x 6",
      "part_cat_id": "14",
      "part_material": "Plastic",
      "colorName": "Tan"
    },
    {
      "inventory_id": "42622",
      "part_num": "3795",
      "color_id": "15",
      "quantity": "1",
      "is_spare": "f",
      "img_url": "https://cdn.rebrickable.com/media/parts/elements/379501.jpg",
      "name": "Plate 2 x 6",
      "part_cat_id": "14",
      "part_material": "Plastic",
      "colorName": "White"
    },
    {
      "inventory_id": "42622",
      "part_num": "3795",
      "color_id": "70",
      "quantity": "1",
      "is_spare": "f",
      "img_url": "https://cdn.rebrickable.com/media/parts/elements/4211247.jpg",
      "name": "Plate 2 x 6",
      "part_cat_id": "14",
      "part_material": "Plastic",
      "colorName": "Reddish Brown"
    },
    {
      "inventory_id": "42622",
      "part_num": "3830",
      "color_id": "84",
      "quantity": "1",
      "is_spare": "f",
      "img_url": "https://cdn.rebrickable.com/media/parts/elements/6162886.jpg",
      "name": "Hinge Brick 1 x 4 [Upper]",
      "part_cat_id": "18",
      "part_material": "Plastic",
      "colorName": "Medium Nougat"
    },
    {
      "inventory_id": "42622",
      "part_num": "3831",
      "color_id": "84",
      "quantity": "1",
      "is_spare": "f",
      "img_url": "https://cdn.rebrickable.com/media/parts/elements/6102967.jpg",
      "name": "Hinge Brick 1 x 4 [Lower]",
      "part_cat_id": "18",
      "part_material": "Plastic",
      "colorName": "Medium Nougat"
    },
    {
      "inventory_id": "42622",
      "part_num": "4032a",
      "color_id": "0",
      "quantity": "5",
      "is_spare": "f",
      "img_url": "https://cdn.rebrickable.com/media/parts/elements/403226.jpg",
      "name": "Plate Round 2 x 2 with Axle Hole Type 1 (+ Opening)",
      "part_cat_id": "21",
      "part_material": "Plastic",
      "colorName": "Black"
    },
    {
      "inventory_id": "42622",
      "part_num": "41682",
      "color_id": "72",
      "quantity": "8",
      "is_spare": "f",
      "img_url": "https://cdn.rebrickable.com/media/parts/elements/6250018.jpg",
      "name": "Bracket 2 x 2 with 1 x 2 Vertical Studs",
      "part_cat_id": "9",
      "part_material": "Plastic",
      "colorName": "Dark Bluish Gray"
    },
    {
      "inventory_id": "42622",
      "part_num": "4216",
      "color_id": "29",
      "quantity": "2",
      "is_spare": "f",
      "img_url": "https://cdn.rebrickable.com/media/parts/elements/6103000.jpg",
      "name": "Brick Special 1 x 2 with Groove",
      "part_cat_id": "5",
      "part_material": "Plastic",
      "colorName": "Bright Pink"
    },
    {
      "inventory_id": "42622",
      "part_num": "4477",
      "color_id": "19",
      "quantity": "2",
      "is_spare": "f",
      "img_url": "https://cdn.rebrickable.com/media/parts/elements/4143409.jpg",
      "name": "Plate 1 x 10",
      "part_cat_id": "14",
      "part_material": "Plastic",
      "colorName": "Tan"
    },
    {
      "inventory_id": "42622",
      "part_num": "4490",
      "color_id": "72",
      "quantity": "1",
      "is_spare": "f",
      "img_url": "https://cdn.rebrickable.com/media/parts/elements/4211120.jpg",
      "name": "Brick Arch 1 x 3",
      "part_cat_id": "37",
      "part_material": "Plastic",
      "colorName": "Dark Bluish Gray"
    },
    {
      "inventory_id": "42622",
      "part_num": "4697b",
      "color_id": "71",
      "quantity": "1",
      "is_spare": "f",
      "img_url": "https://cdn.rebrickable.com/media/parts/elements/4211508.jpg",
      "name": "Pneumatic T-Piece (T Bar) [New Style]",
      "part_cat_id": "22",
      "part_material": "Plastic",
      "colorName": "Light Bluish Gray"
    },
    {
      "inventory_id": "42622",
      "part_num": "4738c",
      "color_id": "84",
      "quantity": "1",
      "is_spare": "f",
      "img_url": "https://cdn.rebrickable.com/media/parts/elements/6102984.jpg",
      "name": "Treasure Chest Bottom with Rear Slots, No Groove",
      "part_cat_id": "7",
      "part_material": "Plastic",
      "colorName": "Medium Nougat"
    },
    {
      "inventory_id": "42622",
      "part_num": "4739a",
      "color_id": "84",
      "quantity": "1",
      "is_spare": "f",
      "img_url": "https://cdn.rebrickable.com/media/parts/elements/6102983.jpg",
      "name": "Treasure Chest Lid [Thick Hinge]",
      "part_cat_id": "7",
      "part_material": "Plastic",
      "colorName": "Medium Nougat"
    },
    {
      "inventory_id": "42622",
      "part_num": "54200",
      "color_id": "70",
      "quantity": "1",
      "is_spare": "f",
      "img_url": "https://cdn.rebrickable.com/media/parts/elements/4260486.jpg",
      "name": "Slope 30 1 x 1 x 2/3 (Cheese Slope)",
      "part_cat_id": "3",
      "part_material": "Plastic",
      "colorName": "Reddish Brown"
    },
    {
      "inventory_id": "42622",
      "part_num": "54200",
      "color_id": "27",
      "quantity": "1",
      "is_spare": "f",
      "img_url": "https://cdn.rebrickable.com/media/parts/elements/4504372.jpg",
      "name": "Slope 30 1 x 1 x 2/3 (Cheese Slope)",
      "part_cat_id": "3",
      "part_material": "Plastic",
      "colorName": "Lime"
    },
    {
      "inventory_id": "42622",
      "part_num": "59443",
      "color_id": "70",
      "quantity": "1",
      "is_spare": "f",
      "img_url": "https://cdn.rebrickable.com/media/parts/elements/4531751.jpg",
      "name": "Technic Axle Connector Smooth [with x Hole + Orientation]",
      "part_cat_id": "12",
      "part_material": "Plastic",
      "colorName": "Reddish Brown"
    },
    {
      "inventory_id": "42622",
      "part_num": "60478",
      "color_id": "0",
      "quantity": "1",
      "is_spare": "f",
      "img_url": "https://cdn.rebrickable.com/media/parts/elements/4515368.jpg",
      "name": "Plate Special 1 x 2 with Handle on End [Closed Ends]",
      "part_cat_id": "9",
      "part_material": "Plastic",
      "colorName": "Black"
    },
    {
      "inventory_id": "42622",
      "part_num": "60592",
      "color_id": "19",
      "quantity": "1",
      "is_spare": "f",
      "img_url": "https://cdn.rebrickable.com/media/parts/elements/4578107.jpg",
      "name": "Window 1 x 2 x 2 Flat Front",
      "part_cat_id": "16",
      "part_material": "Plastic",
      "colorName": "Tan"
    },
    {
      "inventory_id": "42622",
      "part_num": "6111",
      "color_id": "19",
      "quantity": "3",
      "is_spare": "f",
      "img_url": "https://cdn.rebrickable.com/media/parts/elements/4166138.jpg",
      "name": "Brick 1 x 10",
      "part_cat_id": "11",
      "part_material": "Plastic",
      "colorName": "Tan"
    },
    {
      "inventory_id": "42622",
      "part_num": "6141",
      "color_id": "5",
      "quantity": "2",
      "is_spare": "f",
      "img_url": "https://cdn.rebrickable.com/media/parts/elements/4243576.jpg",
      "name": "Plate Round 1 x 1 with Solid Stud",
      "part_cat_id": "21",
      "part_material": "Plastic",
      "colorName": "Dark Pink"
    },
    {
      "inventory_id": "42622",
      "part_num": "6141",
      "color_id": "71",
      "quantity": "2",
      "is_spare": "f",
      "img_url": "https://cdn.rebrickable.com/media/parts/elements/4211525.jpg",
      "name": "Plate Round 1 x 1 with Solid Stud",
      "part_cat_id": "21",
      "part_material": "Plastic",
      "colorName": "Light Bluish Gray"
    },
    {
      "inventory_id": "42622",
      "part_num": "6141",
      "color_id": "10",
      "quantity": "2",
      "is_spare": "f",
      "img_url": "https://cdn.rebrickable.com/media/parts/elements/6109808.jpg",
      "name": "Plate Round 1 x 1 with Solid Stud",
      "part_cat_id": "21",
      "part_material": "Plastic",
      "colorName": "Bright Green"
    },
    {
      "inventory_id": "42622",
      "part_num": "6141",
      "color_id": "25",
      "quantity": "2",
      "is_spare": "f",
      "img_url": "https://cdn.rebrickable.com/media/parts/elements/4157103.jpg",
      "name": "Plate Round 1 x 1 with Solid Stud",
      "part_cat_id": "21",
      "part_material": "Plastic",
      "colorName": "Orange"
    },
    {
      "inventory_id": "42622",
      "part_num": "6141",
      "color_id": "322",
      "quantity": "2",
      "is_spare": "f",
      "img_url": "https://cdn.rebrickable.com/media/parts/elements/6102986.jpg",
      "name": "Plate Round 1 x 1 with Solid Stud",
      "part_cat_id": "21",
      "part_material": "Plastic",
      "colorName": "Medium Azure"
    },
    {
      "inventory_id": "42622",
      "part_num": "61780",
      "color_id": "70",
      "quantity": "1",
      "is_spare": "f",
      "img_url": "https://cdn.rebrickable.com/media/parts/elements/4520638.jpg",
      "name": "Container Box 2 x 2 x 2 - Top Opening",
      "part_cat_id": "7",
      "part_material": "Plastic",
      "colorName": "Reddish Brown"
    },
    {
      "inventory_id": "42622",
      "part_num": "6182",
      "color_id": "84",
      "quantity": "1",
      "is_spare": "f",
      "img_url": "https://cdn.rebrickable.com/media/parts/elements/4569470.jpg",
      "name": "Brick Arch 1 x 4 x 2",
      "part_cat_id": "37",
      "part_material": "Plastic",
      "colorName": "Medium Nougat"
    },
    {
      "inventory_id": "42622",
      "part_num": "63864",
      "color_id": "308",
      "quantity": "13",
      "is_spare": "f",
      "img_url": "https://cdn.rebrickable.com/media/parts/elements/6167928.jpg",
      "name": "Tile 1 x 3",
      "part_cat_id": "19",
      "part_material": "Plastic",
      "colorName": "Dark Brown"
    },
    {
      "inventory_id": "42622",
      "part_num": "63864",
      "color_id": "28",
      "quantity": "4",
      "is_spare": "f",
      "img_url": "https://cdn.rebrickable.com/media/parts/elements/6015452.jpg",
      "name": "Tile 1 x 3",
      "part_cat_id": "19",
      "part_material": "Plastic",
      "colorName": "Dark Tan"
    },
    {
      "inventory_id": "42622",
      "part_num": "63868",
      "color_id": "15",
      "quantity": "1",
      "is_spare": "f",
      "img_url": "https://cdn.rebrickable.com/media/parts/elements/4535737.jpg",
      "name": "Plate Special 1 x 2 with Clip Horizontal on End",
      "part_cat_id": "9",
      "part_material": "Plastic",
      "colorName": "White"
    },
    {
      "inventory_id": "42622",
      "part_num": "63965",
      "color_id": "28",
      "quantity": "1",
      "is_spare": "f",
      "img_url": "https://cdn.rebrickable.com/media/parts/elements/6254772.jpg",
      "name": "Bar 6L with Stop Ring",
      "part_cat_id": "32",
      "part_material": "Plastic",
      "colorName": "Dark Tan"
    },
    {
      "inventory_id": "42622",
      "part_num": "64644",
      "color_id": "308",
      "quantity": "1",
      "is_spare": "f",
      "img_url": "https://cdn.rebrickable.com/media/parts/elements/4538950.jpg",
      "name": "Equipment Telescope / Torch / Spyglass",
      "part_cat_id": "27",
      "part_material": "Plastic",
      "colorName": "Dark Brown"
    },
    {
      "inventory_id": "42622",
      "part_num": "64648",
      "color_id": "25",
      "quantity": "1",
      "is_spare": "f",
      "img_url": "https://cdn.rebrickable.com/media/parts/elements/4623481.jpg",
      "name": "Animal, Fish [Hollow Stud Mouth]",
      "part_cat_id": "28",
      "part_material": "Plastic",
      "colorName": "Orange"
    },
    {
      "inventory_id": "42622",
      "part_num": "6541",
      "color_id": "70",
      "quantity": "3",
      "is_spare": "f",
      "img_url": "https://cdn.rebrickable.com/media/parts/elements/4620075.jpg",
      "name": "Technic Brick 1 x 1 with Hole",
      "part_cat_id": "8",
      "part_material": "Plastic",
      "colorName": "Reddish Brown"
    },
    {
      "inventory_id": "42622",
      "part_num": "65509",
      "color_id": "19",
      "quantity": "2",
      "is_spare": "f",
      "img_url": "https://cdn.rebrickable.com/media/parts/elements/6294227.jpg",
      "name": "Plate Special 2 x 4 with Groove and Two Center Studs (Jumper)",
      "part_cat_id": "9",
      "part_material": "Plastic",
      "colorName": "Tan"
    },
    {
      "inventory_id": "42622",
      "part_num": "65509",
      "color_id": "484",
      "quantity": "2",
      "is_spare": "f",
      "img_url": "https://cdn.rebrickable.com/media/parts/elements/6288614.jpg",
      "name": "Plate Special 2 x 4 with Groove and Two Center Studs (Jumper)",
      "part_cat_id": "9",
      "part_material": "Plastic",
      "colorName": "Dark Orange"
    },
    {
      "inventory_id": "42622",
      "part_num": "65510",
      "color_id": "70",
      "quantity": "1",
      "is_spare": "f",
      "img_url": "https://cdn.rebrickable.com/media/parts/elements/6288630.jpg",
      "name": "Weapon Crossbow and Bolt, Blocky",
      "part_cat_id": "27",
      "part_material": "Plastic",
      "colorName": "Reddish Brown"
    },
    {
      "inventory_id": "42622",
      "part_num": "6636",
      "color_id": "71",
      "quantity": "1",
      "is_spare": "f",
      "img_url": "https://cdn.rebrickable.com/media/parts/elements/4211549.jpg",
      "name": "Tile 1 x 6 with Groove",
      "part_cat_id": "19",
      "part_material": "Plastic",
      "colorName": "Light Bluish Gray"
    },
    {
      "inventory_id": "42622",
      "part_num": "85543",
      "color_id": "15",
      "quantity": "1",
      "is_spare": "f",
      "img_url": "https://cdn.rebrickable.com/media/parts/elements/4544140.jpg",
      "name": "Rubber Belt Small [15mm ID] [Round Cross Section]",
      "part_cat_id": "31",
      "part_material": "Rubber",
      "colorName": "White"
    },
    {
      "inventory_id": "42622",
      "part_num": "87079",
      "color_id": "28",
      "quantity": "6",
      "is_spare": "f",
      "img_url": "https://cdn.rebrickable.com/media/parts/elements/6164288.jpg",
      "name": "Tile 2 x 4 with Groove",
      "part_cat_id": "19",
      "part_material": "Plastic",
      "colorName": "Dark Tan"
    },
    {
      "inventory_id": "42622",
      "part_num": "87580",
      "color_id": "72",
      "quantity": "1",
      "is_spare": "f",
      "img_url": "https://cdn.rebrickable.com/media/parts/elements/4565322.jpg",
      "name": "Plate Special 2 x 2 with Groove and Center Stud (Jumper)",
      "part_cat_id": "9",
      "part_material": "Plastic",
      "colorName": "Dark Bluish Gray"
    },
    {
      "inventory_id": "42622",
      "part_num": "87580",
      "color_id": "14",
      "quantity": "1",
      "is_spare": "f",
      "img_url": "https://cdn.rebrickable.com/media/parts/elements/4565386.jpg",
      "name": "Plate Special 2 x 2 with Groove and Center Stud (Jumper)",
      "part_cat_id": "9",
      "part_material": "Plastic",
      "colorName": "Yellow"
    },
    {
      "inventory_id": "42622",
      "part_num": "87580",
      "color_id": "28",
      "quantity": "24",
      "is_spare": "f",
      "img_url": "https://cdn.rebrickable.com/media/parts/elements/4578032.jpg",
      "name": "Plate Special 2 x 2 with Groove and Center Stud (Jumper)",
      "part_cat_id": "9",
      "part_material": "Plastic",
      "colorName": "Dark Tan"
    },
    {
      "inventory_id": "42622",
      "part_num": "92438",
      "color_id": "326",
      "quantity": "1",
      "is_spare": "f",
      "img_url": "https://cdn.rebrickable.com/media/parts/elements/6272108.jpg",
      "name": "Plate 8 x 16",
      "part_cat_id": "14",
      "part_material": "Plastic",
      "colorName": "Olive Green"
    },
    {
      "inventory_id": "42622",
      "part_num": "96874",
      "color_id": "25",
      "quantity": "1",
      "is_spare": "f",
      "img_url": "https://cdn.rebrickable.com/media/parts/elements/4654448.jpg",
      "name": "Brick and Axle Separator v2.0",
      "part_cat_id": "56",
      "part_material": "Plastic",
      "colorName": "Orange"
    },
    {
      "inventory_id": "42622",
      "part_num": "99207",
      "color_id": "0",
      "quantity": "8",
      "is_spare": "f",
      "img_url": "https://cdn.rebrickable.com/media/parts/elements/6000650.jpg",
      "name": "Bracket 1 x 2 - 2 x 2 Inverted",
      "part_cat_id": "9",
      "part_material": "Plastic",
      "colorName": "Black"
    }
  ],
  "spareParts": [
    {
      "inventory_id": "42622",
      "part_num": "2780",
      "color_id": "0",
      "quantity": "1",
      "is_spare": "t",
      "img_url": "https://cdn.rebrickable.com/media/parts/elements/4121715.jpg",
      "name": "Technic Pin with Friction Ridges Lengthwise and Center Slots",
      "part_cat_id": "53",
      "part_material": "Plastic",
      "colorName": "Black"
    }
  ],
  "setInfo": {
    "set_num": "21160-1",
    "name": "The Illager Raid",
    "year": "2020",
    "theme_id": "577",
    "num_parts": "562",
    "img_url": "https://cdn.rebrickable.com/media/sets/21160-1.jpg"
  },
  "countedUniqueParts": 175,
  "countedSpareParts": 1,
  "countedStandardParts": 546,
  "minfigSetParts": [
    [
      {
        "inventory_id": "59129",
        "part_num": "19729pr0025",
        "color_id": "320",
        "quantity": "1",
        "is_spare": "f",
        "img_url": "https://cdn.rebrickable.com/media/parts/elements/6290430.jpg",
        "name": "Minifig Head Special, Cube with Pixelated Eyes, Eyebrows and Yellow Skin Print (Ninjago Kai)",
        "part_cat_id": "59",
        "part_material": "Plastic",
        "colorName": "Dark Red",
        "fig_num": "fig-006541"
      },
      {
        "inventory_id": "59129",
        "part_num": "970c22",
        "color_id": "4",
        "quantity": "1",
        "is_spare": "f",
        "img_url": "https://cdn.rebrickable.com/media/parts/elements/4582576.jpg",
        "name": "Hips and Red Legs",
        "part_cat_id": "61",
        "part_material": "Plastic",
        "colorName": "Red",
        "fig_num": "fig-006541"
      },
      {
        "inventory_id": "59129",
        "part_num": "973c22h03pr5013",
        "color_id": "4",
        "quantity": "1",
        "is_spare": "f",
        "img_url": "https://cdn.rebrickable.com/media/parts/elements/6290535.jpg",
        "name": "Torso Robes, Pixelated Black and Gold Squares Print, Red Arms, Black Hands",
        "part_cat_id": "60",
        "part_material": "Plastic",
        "colorName": "Red",
        "fig_num": "fig-006541"
      }
    ],
    [
      {
        "inventory_id": "59130",
        "part_num": "25047pr0024",
        "color_id": "92",
        "quantity": "1",
        "is_spare": "f",
        "img_url": "https://cdn.rebrickable.com/media/parts/elements/6290527.jpg",
        "name": "Minifig Head Special, Cube with Nose and Villager Face with Green Eyes Print",
        "part_cat_id": "59",
        "part_material": "Plastic",
        "colorName": "Nougat",
        "fig_num": "fig-006542"
      },
      {
        "inventory_id": "59130",
        "part_num": "25767pr0004",
        "color_id": "19",
        "quantity": "1",
        "is_spare": "f",
        "img_url": "https://cdn.rebrickable.com/media/parts/elements/6290278.jpg",
        "name": "Torso Special, Long with Folded Arms with Pixelated Purple, Orange and Green Squares Print",
        "part_cat_id": "60",
        "part_material": "Plastic",
        "colorName": "Tan",
        "fig_num": "fig-006542"
      },
      {
        "inventory_id": "59130",
        "part_num": "41879a",
        "color_id": "288",
        "quantity": "1",
        "is_spare": "f",
        "img_url": "https://cdn.rebrickable.com/media/parts/elements/6088409.jpg",
        "name": "Legs Short",
        "part_cat_id": "61",
        "part_material": "Plastic",
        "colorName": "Dark Green",
        "fig_num": "fig-006542"
      }
    ],
    [
      {
        "inventory_id": "59131",
        "part_num": "25047pr0024",
        "color_id": "92",
        "quantity": "1",
        "is_spare": "f",
        "img_url": "https://cdn.rebrickable.com/media/parts/elements/6290527.jpg",
        "name": "Minifig Head Special, Cube with Nose and Villager Face with Green Eyes Print",
        "part_cat_id": "59",
        "part_material": "Plastic",
        "colorName": "Nougat",
        "fig_num": "fig-006543"
      },
      {
        "inventory_id": "59131",
        "part_num": "25767pr0005",
        "color_id": "19",
        "quantity": "1",
        "is_spare": "f",
        "img_url": "https://cdn.rebrickable.com/media/parts/elements/6290279.jpg",
        "name": "Torso Special, Long with Folded Arms with Pixelated Orange and Green Squares Print",
        "part_cat_id": "60",
        "part_material": "Plastic",
        "colorName": "Tan",
        "fig_num": "fig-006543"
      },
      {
        "inventory_id": "59131",
        "part_num": "41879a",
        "color_id": "288",
        "quantity": "1",
        "is_spare": "f",
        "img_url": "https://cdn.rebrickable.com/media/parts/elements/6088409.jpg",
        "name": "Legs Short",
        "part_cat_id": "61",
        "part_material": "Plastic",
        "colorName": "Dark Green",
        "fig_num": "fig-006543"
      }
    ],
    [
      {
        "inventory_id": "59132",
        "part_num": "25047pr0020",
        "color_id": "71",
        "quantity": "1",
        "is_spare": "f",
        "img_url": "https://cdn.rebrickable.com/media/parts/elements/6289877.jpg",
        "name": "Minifig Head Special, Cube with Nose and Villager Face with Blue Eyes Print",
        "part_cat_id": "59",
        "part_material": "Plastic",
        "colorName": "Light Bluish Gray",
        "fig_num": "fig-006544"
      },
      {
        "inventory_id": "59132",
        "part_num": "28974",
        "color_id": "72",
        "quantity": "1",
        "is_spare": "f",
        "img_url": "https://cdn.rebrickable.com/media/parts/elements/6170811.jpg",
        "name": "Minifig Neckwear Bracket [One Stud] - Reinforced",
        "part_cat_id": "27",
        "part_material": "Plastic",
        "colorName": "Dark Bluish Gray",
        "fig_num": "fig-006544"
      },
      {
        "inventory_id": "59132",
        "part_num": "970c03",
        "color_id": "0",
        "quantity": "1",
        "is_spare": "f",
        "img_url": "https://cdn.rebrickable.com/media/parts/elements/4569093.jpg",
        "name": "Hips and Black Legs",
        "part_cat_id": "61",
        "part_material": "Plastic",
        "colorName": "Black",
        "fig_num": "fig-006544"
      },
      {
        "inventory_id": "59132",
        "part_num": "973c10h14pr5004",
        "color_id": "320",
        "quantity": "1",
        "is_spare": "f",
        "img_url": "https://cdn.rebrickable.com/media/parts/elements/6290186.jpg",
        "name": "Torso Pixelated Plaid and Belt Print, Dark Red Arms, Light Bluish Gray Hands",
        "part_cat_id": "60",
        "part_material": "Plastic",
        "colorName": "Dark Red",
        "fig_num": "fig-006544"
      }
    ],
    [
      {
        "inventory_id": "59133",
        "part_num": "25047pr0020",
        "color_id": "71",
        "quantity": "1",
        "is_spare": "f",
        "img_url": "https://cdn.rebrickable.com/media/parts/elements/6289877.jpg",
        "name": "Minifig Head Special, Cube with Nose and Villager Face with Blue Eyes Print",
        "part_cat_id": "59",
        "part_material": "Plastic",
        "colorName": "Light Bluish Gray",
        "fig_num": "fig-006545"
      },
      {
        "inventory_id": "59133",
        "part_num": "970c05",
        "color_id": "272",
        "quantity": "1",
        "is_spare": "f",
        "img_url": "https://cdn.rebrickable.com/media/parts/elements/4162916.jpg",
        "name": "Hips and Dark Blue Legs",
        "part_cat_id": "61",
        "part_material": "Plastic",
        "colorName": "Dark Blue",
        "fig_num": "fig-006545"
      },
      {
        "inventory_id": "59133",
        "part_num": "973c07h14pr5007",
        "color_id": "308",
        "quantity": "1",
        "is_spare": "f",
        "img_url": "https://cdn.rebrickable.com/media/parts/elements/6290274.jpg",
        "name": "Torso Pixelated Black, Dark Red, and Silver Squares (Buttons) Print, Dark Brown Arms, Light Bluish Gray Hands",
        "part_cat_id": "60",
        "part_material": "Plastic",
        "colorName": "Dark Brown",
        "fig_num": "fig-006545"
      }
    ]
  ]
}