{
  "standard": [
    {
      "inventory_id": "25032",
      "part_num": "2032",
      "color_id": "4",
      "quantity": "1",
      "is_spare": "f",
      "img_url": "https://cdn.rebrickable.com/media/parts/photos/4/2032-4-cb509351-8fb8-4e13-b1ec-dcc96bfe3f17.jpg",
      "name": "Duplo Train Wagon",
      "part_cat_id": "4",
      "part_material": "Plastic",
      "colorName": "Red"
    },
    {
      "inventory_id": "25032",
      "part_num": "3437",
      "color_id": "1",
      "quantity": "1",
      "is_spare": "f",
      "img_url": "https://cdn.rebrickable.com/media/parts/elements/343723.jpg",
      "name": "Duplo Brick 2 x 2",
      "part_cat_id": "4",
      "part_material": "Plastic",
      "colorName": "Blue"
    },
    {
      "inventory_id": "25032",
      "part_num": "4009pr0001",
      "color_id": "7",
      "quantity": "1",
      "is_spare": "f",
      "img_url": "https://cdn.rebrickable.com/media/parts/photos/7/4009pr0001-7-e7a56ab8-9cbf-48a0-8aa1-cbefc20cd353.jpg",
      "name": "Duplo Animal Horse / Pony, Eyes Solid Black",
      "part_cat_id": "4",
      "part_material": "Plastic",
      "colorName": "Light Gray"
    },
    {
      "inventory_id": "25032",
      "part_num": "4543",
      "color_id": "4",
      "quantity": "1",
      "is_spare": "f",
      "img_url": "https://cdn.rebrickable.com/media/parts/elements/4205308.jpg",
      "name": "Duplo Backhoe / Train Cabin Roof",
      "part_cat_id": "4",
      "part_material": "Plastic",
      "colorName": "Red"
    },
    {
      "inventory_id": "25032",
      "part_num": "4544pr0004",
      "color_id": "14",
      "quantity": "1",
      "is_spare": "f",
      "img_url": "https://cdn.rebrickable.com/media/parts/photos/14/4544pr0004-14-db165ab9-6f5c-452e-94ce-2bda0fc7fb38.jpg",
      "name": "Duplo Train Steam Engine Cabin with Red Oval and '2' Print",
      "part_cat_id": "4",
      "part_material": "Plastic",
      "colorName": "Yellow"
    },
    {
      "inventory_id": "25032",
      "part_num": "4550",
      "color_id": "1",
      "quantity": "1",
      "is_spare": "f",
      "img_url": "https://cdn.rebrickable.com/media/parts/photos/1/4550-1-6e8ac3c8-5bc6-4d62-80e4-8ab5fcfa8bdd.jpg",
      "name": "Duplo Train Steam Engine Cow Catcher",
      "part_cat_id": "4",
      "part_material": "Plastic",
      "colorName": "Blue"
    },
    {
      "inventory_id": "25032",
      "part_num": "4555c02pr0046",
      "color_id": "4",
      "quantity": "1",
      "is_spare": "f",
      "img_url": "https://cdn.rebrickable.com/media/parts/photos/4/4555pr0046-4-9020024e-ed2c-4ac6-9488-93938d774d62.jpg",
      "name": "Duplo Figure, Early, with Flat Cap Blue, Blue Legs, Blue Overalls, Turned Down Nose Print",
      "part_cat_id": "57",
      "part_material": "Plastic",
      "colorName": "Red"
    },
    {
      "inventory_id": "25032",
      "part_num": "4559c01",
      "color_id": "1",
      "quantity": "1",
      "is_spare": "f",
      "img_url": "https://cdn.rebrickable.com/media/parts/elements/4263156.jpg",
      "name": "Duplo Train Chassis 2 x 6 with Red Train Wheels and Moveable Hook",
      "part_cat_id": "4",
      "part_material": "Plastic",
      "colorName": "Blue"
    },
    {
      "inventory_id": "25032",
      "part_num": "4570c02",
      "color_id": "1",
      "quantity": "1",
      "is_spare": "f",
      "img_url": "https://cdn.rebrickable.com/media/parts/photos/1/4570c02-1-73b47240-1aa4-48df-b8f9-f92f487c8709.jpg",
      "name": "Duplo Train Steam Engine Funnel Top, Yellow Top",
      "part_cat_id": "4",
      "part_material": "Plastic",
      "colorName": "Blue"
    },
    {
      "inventory_id": "25032",
      "part_num": "4580c01",
      "color_id": "1",
      "quantity": "1",
      "is_spare": "f",
      "img_url": "https://cdn.rebrickable.com/media/parts/elements/4263157.jpg",
      "name": "Duplo Train Chassis with Yellow Drive Rod and Red Wheels",
      "part_cat_id": "4",
      "part_material": "Plastic",
      "colorName": "Blue"
    },
    {
      "inventory_id": "25032",
      "part_num": "4810pr0001",
      "color_id": "15",
      "quantity": "1",
      "is_spare": "f",
      "img_url": "https://cdn.rebrickable.com/media/parts/photos/15/4810pr0001-15-39ac9452-92cf-478a-babd-80e31081ee11.jpg",
      "name": "Duplo Animal Chicken / Hen Tail and Smooth Red Comb - Bottom Stud Holder",
      "part_cat_id": "4",
      "part_material": "Plastic",
      "colorName": "White"
    }
  ],
  "spareParts": [],
  "setInfo": {
    "set_num": "2706-1",
    "name": "Barnyard Express",
    "year": "1988",
    "theme_id": "634",
    "num_parts": "11",
    "img_url": "https://cdn.rebrickable.com/media/sets/2706-1.jpg"
  },
  "countedUniqueParts": 11,
  "countedSpareParts": 0,
  "countedStandardParts": 11,
  "minfigSetParts": []
}