{
  "standard": [
    {
      "inventory_id": "2639",
      "part_num": "2342",
      "color_id": "0",
      "quantity": "1",
      "is_spare": "f",
      "img_url": "https://cdn.rebrickable.com/media/parts/ldraw/0/2342.png",
      "name": "Equipment Control Panel",
      "part_cat_id": "27",
      "part_material": "Plastic",
      "colorName": "Black"
    },
    {
      "inventory_id": "2639",
      "part_num": "298c02",
      "color_id": "7",
      "quantity": "2",
      "is_spare": "f",
      "img_url": "https://cdn.rebrickable.com/media/parts/elements/73588.jpg",
      "name": "Lever Small Base with Black Lever",
      "part_cat_id": "32",
      "part_material": "Plastic",
      "colorName": "Light Gray"
    },
    {
      "inventory_id": "2639",
      "part_num": "3001",
      "color_id": "7",
      "quantity": "1",
      "is_spare": "f",
      "img_url": "https://cdn.rebrickable.com/media/parts/elements/300102.jpg",
      "name": "Brick 2 x 4",
      "part_cat_id": "11",
      "part_material": "Plastic",
      "colorName": "Light Gray"
    },
    {
      "inventory_id": "2639",
      "part_num": "3002",
      "color_id": "7",
      "quantity": "1",
      "is_spare": "f",
      "img_url": "https://cdn.rebrickable.com/media/parts/elements/300202.jpg",
      "name": "Brick 2 x 3",
      "part_cat_id": "11",
      "part_material": "Plastic",
      "colorName": "Light Gray"
    },
    {
      "inventory_id": "2639",
      "part_num": "3020",
      "color_id": "7",
      "quantity": "1",
      "is_spare": "f",
      "img_url": "https://cdn.rebrickable.com/media/parts/elements/302002.jpg",
      "name": "Plate 2 x 4",
      "part_cat_id": "14",
      "part_material": "Plastic",
      "colorName": "Light Gray"
    },
    {
      "inventory_id": "2639",
      "part_num": "3022",
      "color_id": "7",
      "quantity": "2",
      "is_spare": "f",
      "img_url": "https://cdn.rebrickable.com/media/parts/elements/302202.jpg",
      "name": "Plate 2 x 2",
      "part_cat_id": "14",
      "part_material": "Plastic",
      "colorName": "Light Gray"
    },
    {
      "inventory_id": "2639",
      "part_num": "3023",
      "color_id": "7",
      "quantity": "5",
      "is_spare": "f",
      "img_url": "https://cdn.rebrickable.com/media/parts/elements/302302.jpg",
      "name": "Plate 1 x 2",
      "part_cat_id": "14",
      "part_material": "Plastic",
      "colorName": "Light Gray"
    },
    {
      "inventory_id": "2639",
      "part_num": "3024",
      "color_id": "36",
      "quantity": "2",
      "is_spare": "f",
      "img_url": "https://cdn.rebrickable.com/media/parts/elements/3000841.jpg",
      "name": "Plate 1 x 1",
      "part_cat_id": "14",
      "part_material": "Plastic",
      "colorName": "Trans-Red"
    },
    {
      "inventory_id": "2639",
      "part_num": "3039",
      "color_id": "7",
      "quantity": "1",
      "is_spare": "f",
      "img_url": "https://cdn.rebrickable.com/media/parts/elements/303902.jpg",
      "name": "Slope 45 2 x 2",
      "part_cat_id": "3",
      "part_material": "Plastic",
      "colorName": "Light Gray"
    },
    {
      "inventory_id": "2639",
      "part_num": "3039pr9996",
      "color_id": "7",
      "quantity": "1",
      "is_spare": "f",
      "img_url": "https://cdn.rebrickable.com/media/parts/ldraw/7/3039p32.png",
      "name": "Slope 45 2 x 2 with 12 Buttons, 3 Red Lamps, Black Panel Print",
      "part_cat_id": "3",
      "part_material": "Plastic",
      "colorName": "Light Gray"
    },
    {
      "inventory_id": "2639",
      "part_num": "3069b",
      "color_id": "7",
      "quantity": "2",
      "is_spare": "f",
      "img_url": "https://cdn.rebrickable.com/media/parts/elements/306902.jpg",
      "name": "Tile 1 x 2 with Groove",
      "part_cat_id": "19",
      "part_material": "Plastic",
      "colorName": "Light Gray"
    },
    {
      "inventory_id": "2639",
      "part_num": "3069bpr0039",
      "color_id": "7",
      "quantity": "1",
      "is_spare": "f",
      "img_url": "https://cdn.rebrickable.com/media/parts/ldraw/7/3069bp25.png",
      "name": "Tile 1 x 2 with Groove and Space Computer Print",
      "part_cat_id": "19",
      "part_material": "Plastic",
      "colorName": "Light Gray"
    },
    {
      "inventory_id": "2639",
      "part_num": "3297pr0019",
      "color_id": "7",
      "quantity": "1",
      "is_spare": "f",
      "img_url": "https://cdn.rebrickable.com/media/parts/ldraw/7/3297p90.png",
      "name": "Slope 33 3 x 4 with Classic Space Logo Print",
      "part_cat_id": "3",
      "part_material": "Plastic",
      "colorName": "Light Gray"
    },
    {
      "inventory_id": "2639",
      "part_num": "3660",
      "color_id": "7",
      "quantity": "1",
      "is_spare": "f",
      "img_url": "https://cdn.rebrickable.com/media/parts/elements/366002.jpg",
      "name": "Slope Inverted 45 2 x 2 [Ovoid Bottom Pin, Bar-sized Stud Holes]",
      "part_cat_id": "3",
      "part_material": "Plastic",
      "colorName": "Light Gray"
    },
    {
      "inventory_id": "2639",
      "part_num": "3700",
      "color_id": "7",
      "quantity": "1",
      "is_spare": "f",
      "img_url": "https://cdn.rebrickable.com/media/parts/elements/370002.jpg",
      "name": "Technic Brick 1 x 2 [1 Hole]",
      "part_cat_id": "8",
      "part_material": "Plastic",
      "colorName": "Light Gray"
    },
    {
      "inventory_id": "2639",
      "part_num": "3702",
      "color_id": "7",
      "quantity": "2",
      "is_spare": "f",
      "img_url": "https://cdn.rebrickable.com/media/parts/elements/370202.jpg",
      "name": "Technic Brick 1 x 8 [7 Holes]",
      "part_cat_id": "8",
      "part_material": "Plastic",
      "colorName": "Light Gray"
    },
    {
      "inventory_id": "2639",
      "part_num": "3706",
      "color_id": "0",
      "quantity": "3",
      "is_spare": "f",
      "img_url": "https://cdn.rebrickable.com/media/parts/elements/370626.jpg",
      "name": "Technic Axle 6",
      "part_cat_id": "46",
      "part_material": "Plastic",
      "colorName": "Black"
    },
    {
      "inventory_id": "2639",
      "part_num": "3713",
      "color_id": "7",
      "quantity": "6",
      "is_spare": "f",
      "img_url": "https://cdn.rebrickable.com/media/parts/elements/4125313.jpg",
      "name": "Technic Bush",
      "part_cat_id": "54",
      "part_material": "Plastic",
      "colorName": "Light Gray"
    },
    {
      "inventory_id": "2639",
      "part_num": "3959",
      "color_id": "0",
      "quantity": "1",
      "is_spare": "f",
      "img_url": "https://cdn.rebrickable.com/media/parts/elements/395926.jpg",
      "name": "Weapon Gun / Torch (Space) [with Grooves]",
      "part_cat_id": "27",
      "part_material": "Plastic",
      "colorName": "Black"
    },
    {
      "inventory_id": "2639",
      "part_num": "4070",
      "color_id": "7",
      "quantity": "2",
      "is_spare": "f",
      "img_url": "https://cdn.rebrickable.com/media/parts/elements/407002.jpg",
      "name": "Brick Special 1 x 1 with Headlight and No Slot",
      "part_cat_id": "5",
      "part_material": "Plastic",
      "colorName": "Light Gray"
    },
    {
      "inventory_id": "2639",
      "part_num": "4085b",
      "color_id": "7",
      "quantity": "4",
      "is_spare": "f",
      "img_url": "https://cdn.rebrickable.com/media/parts/ldraw/7/4085b.png",
      "name": "Plate Special 1 x 1 with Clip Vertical [Thin U Clip]",
      "part_cat_id": "9",
      "part_material": "Plastic",
      "colorName": "Light Gray"
    },
    {
      "inventory_id": "2639",
      "part_num": "4288",
      "color_id": "0",
      "quantity": "6",
      "is_spare": "f",
      "img_url": "https://cdn.rebrickable.com/media/parts/ldraw/0/4288.png",
      "name": "Wheel Full Rubber Balloon with Axle hole",
      "part_cat_id": "29",
      "part_material": "Plastic",
      "colorName": "Black"
    },
    {
      "inventory_id": "2639",
      "part_num": "4315",
      "color_id": "7",
      "quantity": "1",
      "is_spare": "f",
      "img_url": "https://cdn.rebrickable.com/media/parts/ldraw/7/4315.png",
      "name": "Hinge Vehicle Roof Holder 1 x 4",
      "part_cat_id": "18",
      "part_material": "Plastic",
      "colorName": "Light Gray"
    },
    {
      "inventory_id": "2639",
      "part_num": "4345a",
      "color_id": "7",
      "quantity": "2",
      "is_spare": "f",
      "img_url": "https://cdn.rebrickable.com/media/parts/ldraw/7/4345a.png",
      "name": "Box 2 x 2 x 2 [Solid Studs]",
      "part_cat_id": "7",
      "part_material": "Plastic",
      "colorName": "Light Gray"
    },
    {
      "inventory_id": "2639",
      "part_num": "4346",
      "color_id": "7",
      "quantity": "2",
      "is_spare": "f",
      "img_url": "https://cdn.rebrickable.com/media/parts/elements/434602.jpg",
      "name": "Box 2 x 2 x 2 Door with Slot",
      "part_cat_id": "7",
      "part_material": "Plastic",
      "colorName": "Light Gray"
    },
    {
      "inventory_id": "2639",
      "part_num": "4349",
      "color_id": "0",
      "quantity": "1",
      "is_spare": "f",
      "img_url": "https://cdn.rebrickable.com/media/parts/elements/434926.jpg",
      "name": "Equipment Weapon, Loudhailer / Blaster / Space Gun",
      "part_cat_id": "27",
      "part_material": "Plastic",
      "colorName": "Black"
    },
    {
      "inventory_id": "2639",
      "part_num": "4474",
      "color_id": "34",
      "quantity": "1",
      "is_spare": "f",
      "img_url": "https://cdn.rebrickable.com/media/parts/ldraw/34/4474.png",
      "name": "Windscreen 6 x 4 x 2 Canopy",
      "part_cat_id": "47",
      "part_material": "Plastic",
      "colorName": "Trans-Green"
    },
    {
      "inventory_id": "2639",
      "part_num": "4479",
      "color_id": "0",
      "quantity": "1",
      "is_spare": "f",
      "img_url": "https://cdn.rebrickable.com/media/parts/elements/4212278.jpg",
      "name": "Equipment Metal Detector",
      "part_cat_id": "27",
      "part_material": "Plastic",
      "colorName": "Black"
    },
    {
      "inventory_id": "2639",
      "part_num": "4595",
      "color_id": "0",
      "quantity": "2",
      "is_spare": "f",
      "img_url": "https://cdn.rebrickable.com/media/parts/elements/4190471.jpg",
      "name": "Brick Special 1 x 2 x 2/3 with Studs on Sides",
      "part_cat_id": "5",
      "part_material": "Plastic",
      "colorName": "Black"
    },
    {
      "inventory_id": "2639",
      "part_num": "4730",
      "color_id": "7",
      "quantity": "1",
      "is_spare": "f",
      "img_url": "https://cdn.rebrickable.com/media/parts/ldraw/7/4730.png",
      "name": "Brick Special 2 x 2 with Pin and No Axle Hole",
      "part_cat_id": "5",
      "part_material": "Plastic",
      "colorName": "Light Gray"
    },
    {
      "inventory_id": "2639",
      "part_num": "4735",
      "color_id": "0",
      "quantity": "1",
      "is_spare": "f",
      "img_url": "https://cdn.rebrickable.com/media/parts/elements/4141580.jpg",
      "name": "Bar 1 x 3 [Clip / Anti-Stud]",
      "part_cat_id": "32",
      "part_material": "Plastic",
      "colorName": "Black"
    },
    {
      "inventory_id": "2639",
      "part_num": "4740",
      "color_id": "36",
      "quantity": "2",
      "is_spare": "f",
      "img_url": "https://cdn.rebrickable.com/media/parts/elements/4142995.jpg",
      "name": "Dish 2 x 2 Inverted [Radar]",
      "part_cat_id": "21",
      "part_material": "Plastic",
      "colorName": "Trans-Red"
    },
    {
      "inventory_id": "2639",
      "part_num": "6141",
      "color_id": "36",
      "quantity": "2",
      "is_spare": "f",
      "img_url": "https://cdn.rebrickable.com/media/parts/elements/3005741.jpg",
      "name": "Plate Round 1 x 1 with Solid Stud",
      "part_cat_id": "21",
      "part_material": "Plastic",
      "colorName": "Trans-Red"
    },
    {
      "inventory_id": "2639",
      "part_num": "73590c01a",
      "color_id": "7",
      "quantity": "2",
      "is_spare": "f",
      "img_url": "https://cdn.rebrickable.com/media/parts/ldraw/7/73590a.png",
      "name": "Flexible Hose 8.5L with Tabless Ends (Ends same color as Tube)",
      "part_cat_id": "30",
      "part_material": "Plastic",
      "colorName": "Light Gray"
    }
  ],
  "spareParts": [
    {
      "inventory_id": "2639",
      "part_num": "6141",
      "color_id": "36",
      "quantity": "2",
      "is_spare": "t",
      "img_url": "https://cdn.rebrickable.com/media/parts/elements/3005741.jpg",
      "name": "Plate Round 1 x 1 with Solid Stud",
      "part_cat_id": "21",
      "part_material": "Plastic",
      "colorName": "Trans-Red"
    }
  ],
  "setInfo": {
    "set_num": "1580-1",
    "name": "Lunar Scout",
    "year": "1986",
    "theme_id": "130",
    "num_parts": "70",
    "img_url": "https://cdn.rebrickable.com/media/sets/1580-1.jpg"
  },
  "countedUniqueParts": 35,
  "countedSpareParts": 2,
  "countedStandardParts": 65,
  "minfigSetParts": [
    [
      {
        "inventory_id": "51557",
        "part_num": "3626apr0001",
        "color_id": "14",
        "quantity": "1",
        "is_spare": "f",
        "img_url": "https://cdn.rebrickable.com/media/parts/ldraw/14/3626ap01.png",
        "name": "Minifig Head Standard Grin Print [Solid Stud]",
        "part_cat_id": "59",
        "part_material": "Plastic",
        "colorName": "Yellow",
        "fig_num": "fig-000742"
      },
      {
        "inventory_id": "51557",
        "part_num": "3838",
        "color_id": "1",
        "quantity": "1",
        "is_spare": "f",
        "img_url": "https://cdn.rebrickable.com/media/parts/elements/6069889.jpg",
        "name": "Minifig Neckwear Airtanks",
        "part_cat_id": "27",
        "part_material": "Plastic",
        "colorName": "Blue",
        "fig_num": "fig-000742"
      },
      {
        "inventory_id": "51557",
        "part_num": "3842b",
        "color_id": "1",
        "quantity": "1",
        "is_spare": "f",
        "img_url": "https://cdn.rebrickable.com/media/parts/ldraw/1/3842b.png",
        "name": "Helmet Classic with Thick Chin Guard and Visor Dimples",
        "part_cat_id": "65",
        "part_material": "Plastic",
        "colorName": "Blue",
        "fig_num": "fig-000742"
      },
      {
        "inventory_id": "51557",
        "part_num": "970c28",
        "color_id": "1",
        "quantity": "1",
        "is_spare": "f",
        "img_url": "https://cdn.rebrickable.com/media/parts/elements/4583501.jpg",
        "name": "Hips and Blue Legs",
        "part_cat_id": "61",
        "part_material": "Plastic",
        "colorName": "Blue",
        "fig_num": "fig-000742"
      },
      {
        "inventory_id": "51557",
        "part_num": "973c28h28pr1594",
        "color_id": "1",
        "quantity": "1",
        "is_spare": "f",
        "img_url": "https://cdn.rebrickable.com/media/parts/elements/6045866.jpg",
        "name": "Torso Classic Moon Print, Blue Arms and Hands",
        "part_cat_id": "60",
        "part_material": "Plastic",
        "colorName": "Blue",
        "fig_num": "fig-000742"
      }
    ]
  ]
}